labs_backup/backup_lab11/lab11/ex_array/design_src/array.v
module array (
    input clk,
    input rst_n,
    output reg w_ready,
    input w_valid,
    input [7:0] w_data
);
    reg [7:0] R[0:7] /* verilator public */;
    reg [7:0] R_nxt[0:7];

    reg [3:0] p, p_nxt;

    reg w_fire;
    
    integer i;

    always @(*) begin
        w_fire = w_ready & w_valid;
        for (i = 0; i < 8; i = i + 1) begin
            R_nxt[i] = ((p == i) && (w_fire)) ? w_data : R[i];
        end
        p_nxt = w_fire ? p + 1 : p;
    end

    always @(posedge clk, negedge rst_n) begin
        if (~rst_n) begin
            for (i = 0; i < 8; i = i + 1) begin
                R[i] <= 0;
            end
            p <= 0;
        end
        else begin
            for (i = 0; i < 8; i = i + 1) begin
                R[i] <= R_nxt[i];
            end
            p <= p_nxt;
        end
    end

    always @(*) begin
        w_ready = ~p[3]; // !(p == 8)
    end
endmodule

labs_backup/backup_lab11/ex_array/golden/golden_wave.vcd
$version Generated by VerilatedVcd $end
$timescale 1ps $end
 $scope module TOP $end
  $scope module array $end
   $var wire 1 ( clk $end
   $var wire 1 ) rst_n $end
   $var wire 1 * w_ready $end
   $var wire 1 + w_valid $end
   $var wire 8 , w_data [7:0] $end
   $var wire 8 - R[0] [7:0] $end
   $var wire 8 . R[1] [7:0] $end
   $var wire 8 / R[2] [7:0] $end
   $var wire 8 0 R[3] [7:0] $end
   $var wire 8 1 R[4] [7:0] $end
   $var wire 8 2 R[5] [7:0] $end
   $var wire 8 3 R[6] [7:0] $end
   $var wire 8 4 R[7] [7:0] $end
   $var wire 8 5 R_nxt[0] [7:0] $end
   $var wire 8 6 R_nxt[1] [7:0] $end
   $var wire 8 7 R_nxt[2] [7:0] $end
   $var wire 8 8 R_nxt[3] [7:0] $end
   $var wire 8 9 R_nxt[4] [7:0] $end
   $var wire 8 : R_nxt[5] [7:0] $end
   $var wire 8 ; R_nxt[6] [7:0] $end
   $var wire 8 < R_nxt[7] [7:0] $end
   $var wire 4 = p [3:0] $end
   $var wire 4 > p_nxt [3:0] $end
   $var wire 1 ? w_fire $end
   $var wire 32 @ i [31:0] $end
  $upscope $end
  $var wire 1 # clk $end
  $var wire 1 $ rst_n $end
  $var wire 1 % w_ready $end
  $var wire 1 & w_valid $end
  $var wire 8 ' w_data [7:0] $end
 $upscope $end
$enddefinitions $end


#5
0#
0$
1%
0&
b00000000 '
0(
0)
1*
0+
b00000000 ,
b00000000 -
b00000000 .
b00000000 /
b00000000 0
b00000000 1
b00000000 2
b00000000 3
b00000000 4
b00000000 5
b00000000 6
b00000000 7
b00000000 8
b00000000 9
b00000000 :
b00000000 ;
b00000000 <
b0000 =
b0000 >
0?
b00000000000000000000000000001000 @
#10
#15
#20
1#
1(
#25
0#
0(
#30
1#
1(
#35
0#
1$
0(
1)
#40
1#
1(
#45
0#
0(
#50
1#
1(
#55
0#
0(
#60
1#
1(
#65
0#
1&
b00001010 '
0(
1+
b00001010 ,
b00001010 5
b0001 >
1?
#70
1#
1(
b00001010 -
b00001010 6
b0001 =
b0010 >
#75
0#
b00000000 '
0(
b00000000 ,
b00000000 6
#80
1#
1(
b0010 =
b0011 >
#85
0#
0&
0(
0+
b0010 >
0?
#90
1#
1(
#95
0#
1&
b00000110 '
0(
1+
b00000110 ,
b00000110 7
b0011 >
1?
#100
1#
1(
b00000110 /
b00000110 8
b0011 =
b0100 >
#105
0#
0&
b00000000 '
0(
0+
b00000000 ,
b00000000 8
b0011 >
0?
#110
1#
1(
#115
0#
0(
#120
1#
1(
#125
0#
0(
#130
1#
1(
#135
0#
1&
b00000101 '
0(
1+
b00000101 ,
b00000101 8
b0100 >
1?
#140
1#
1(
b00000101 0
b00000101 9
b0100 =
b0101 >
#145
0#
0&
b00000000 '
0(
0+
b00000000 ,
b00000000 9
b0100 >
0?
