labs_backup/backup_lab10/pr_divmod/design_src/divmod.v
module divmod (
    input            clk,
    input            rst_n,
    input            valid,
    input      [7:0] dividend,
    input      [7:0] divisor,
    output reg       ready,
    output reg [7:0] quotient,
    output reg [7:0] remainder
);
    localparam IDLE = 0,
               BUSY = 1,
               OUT  = 2;
    
    reg [1:0] S, S_nxt;
    reg [7:0] a, a_nxt;
    reg [7:0] b, b_nxt;
    reg [7:0] q, q_nxt;

    always @(*) begin
        case (S)
            IDLE: begin
                if (valid) begin
                    a_nxt = dividend;
                    b_nxt = divisor;
                    q_nxt = 0;
                    S_nxt = BUSY;
                end
                else begin
                    a_nxt = a;
                    b_nxt = b;
                    q_nxt = 0;
                    S_nxt = IDLE;
                end
            end
            BUSY: begin
                if (a < b) begin
                    a_nxt = a;
                    b_nxt = b;
                    q_nxt = q;
                    S_nxt = OUT;
                end
                else begin
                    a_nxt = a - b;
                    b_nxt = b;
                    q_nxt = q + 1;
                    S_nxt = BUSY;
                end
            end
            OUT: begin
                a_nxt = a;
                b_nxt = b;
                q_nxt = q;
                S_nxt = IDLE;
            end
            default: begin
                a_nxt = 0;
                b_nxt = 0;
                q_nxt = 0;
                S_nxt = IDLE;
            end
        endcase
    end

    always @(posedge clk, negedge rst_n) begin
        if (~rst_n) begin
            S <= IDLE;
            a <= 0;
            b <= 0;
            q <= 0;
        end
        else begin
            S <= S_nxt;
            a <= a_nxt;
            b <= b_nxt;
            q <= q_nxt;
        end
    end

    always @(*) begin
        ready = S == OUT;
        quotient = S == OUT ? q : 0;
        remainder = S == OUT ? a : 0;
    end
endmodule

labs_backup/backup_lab10/pr_divmod/golden/golden_wave.vcd
$version Generated by VerilatedVcd $end
$timescale 1ps $end
 $scope module TOP $end
  $var wire 1 # clk $end
  $var wire 1 $ rst_n $end
  $var wire 1 % valid $end
  $var wire 8 & dividend [7:0] $end
  $var wire 8 ' divisor [7:0] $end
  $var wire 1 ( ready $end
  $var wire 8 ) quotient [7:0] $end
  $var wire 8 * remainder [7:0] $end
  $scope module divmod $end
   $var wire 1 + clk $end
   $var wire 1 , rst_n $end
   $var wire 1 - valid $end
   $var wire 8 . dividend [7:0] $end
   $var wire 8 / divisor [7:0] $end
   $var wire 1 0 ready $end
   $var wire 8 1 quotient [7:0] $end
   $var wire 8 2 remainder [7:0] $end
   $var wire 32 ; IDLE [31:0] $end
   $var wire 32 < BUSY [31:0] $end
   $var wire 32 = OUT [31:0] $end
   $var wire 2 3 S [1:0] $end
   $var wire 2 4 S_nxt [1:0] $end
   $var wire 8 5 a [7:0] $end
   $var wire 8 6 a_nxt [7:0] $end
   $var wire 8 7 b [7:0] $end
   $var wire 8 8 b_nxt [7:0] $end
   $var wire 8 9 q [7:0] $end
   $var wire 8 : q_nxt [7:0] $end
  $upscope $end
 $upscope $end
$enddefinitions $end


#5
0#
0$
0%
b00000000 &
b00000000 '
0(
b00000000 )
b00000000 *
0+
0,
0-
b00000000 .
b00000000 /
00
b00000000 1
b00000000 2
b00 3
b00 4
b00000000 5
b00000000 6
b00000000 7
b00000000 8
b00000000 9
b00000000 :
b00000000000000000000000000000000 ;
b00000000000000000000000000000001 <
b00000000000000000000000000000010 =
#10
#15
#20
1#
1+
#25
0#
0+
#30
1#
1+
#35
0#
1$
0+
1,
#40
1#
1+
#45
0#
1%
b00001000 &
b00000010 '
0+
1-
b00001000 .
b00000010 /
b01 4
b00001000 6
b00000010 8
#50
1#
1+
b01 3
b00001000 5
b00000110 6
b00000010 7
b00000001 :
#55
0#
0%
b00000000 &
b00000000 '
0+
0-
b00000000 .
b00000000 /
#60
1#
1+
b00000110 5
b00000100 6
b00000001 9
b00000010 :
#65
0#
0+
#70
1#
1+
b00000100 5
b00000010 6
b00000010 9
b00000011 :
#75
0#
0+
#80
1#
1+
b00000010 5
b00000000 6
b00000011 9
b00000100 :
#85
0#
0+
#90
1#
1+
b10 4
b00000000 5
b00000100 9
#95
0#
0+
#100
1#
1(
b00000100 )
1+
10
b00000100 1
b10 3
b00 4
#105
0#
0+
#110
1#
0(
b00000000 )
1+
00
b00000000 1
b00 3
b00000000 :
#115
0#
0+
#120
1#
1+
b00000000 9
#125
0#
0+
#130
1#
1+
#135
0#
0+
#140
1#
1+
#145
0#
0+
#150
1#
1+
#155
0#
0+
#160
1#
1+
#165
0#
0+
#170
1#
1+
#175
0#
0+
#180
1#
1+
#185
0#
0+
#190
1#
1+
#195
0#
0+
#200
1#
1+
#205
0#
0$
0+
0,
b00000000 7
b00000000 8
#215
#225
#235
#245
#250
1$
1%
b00010011 &
b00000011 '
1,
1-
b00010011 .
b00000011 /
b01 4
b00010011 6
b00000011 8
#255
1#
1+
b01 3
b00010011 5
b00010000 6
b00000011 7
b00000001 :
#260
0#
0%
b00000000 &
b00000000 '
0+
0-
b00000000 .
b00000000 /
#265
1#
1+
b00010000 5
b00001101 6
b00000001 9
b00000010 :
#270
0#
0+
#275
1#
1+
b00001101 5
b00001010 6
b00000010 9
b00000011 :
#280
0#
0+
#285
1#
1+
b00001010 5
b00000111 6
b00000011 9
b00000100 :
#290
0#
0+
#295
1#
1+
b00000111 5
b00000100 6
b00000100 9
b00000101 :
#300
0#
0+
#305
1#
1+
b00000100 5
b00000001 6
b00000101 9
b00000110 :
#310
0#
0+
#315
1#
1+
b10 4
b00000001 5
b00000110 9
#320
0#
0+
#325
1#
1(
b00000110 )
b00000001 *
1+
10
b00000110 1
b00000001 2
b10 3
b00 4
#330
0#
0+
#335
1#
0(
b00000000 )
b00000000 *
1+
00
b00000000 1
b00000000 2
b00 3
b00000000 :
#340
0#
0+
#345
1#
1+
b00000000 9
#350
0#
0+
#355
1#
1+
#360
0#
0+
#365
1#
1+
#370
0#
0+
#375
1#
1+
#380
0#
0+
#385
1#
1+
#390
0#
0+
#395
1#
1+
#400
0#
0+
#405
1#
1+
#410
0#
0+
#415
1#
1+
#420
0#
0+
#425
1#
1+
#430
0#
0$
0+
0,
b00000000 5
b00000000 6
b00000000 7
b00000000 8
#440
#450
#460
#470
#475
1$
1%
b00000010 &
b00000101 '
1,
1-
b00000010 .
b00000101 /
b01 4
b00000010 6
b00000101 8
#480
1#
1+
b01 3
b10 4
b00000010 5
b00000101 7
#485
0#
0%
b00000000 &
b00000000 '
0+
0-
b00000000 .
b00000000 /
#490
1#
1(
b00000010 *
1+
10
b00000010 2
b10 3
b00 4
#495
0#
0+
#500
1#
0(
b00000000 *
1+
00
b00000000 2
b00 3
#505
0#
0+
#510
1#
1+
#515
0#
0+
#520
1#
1+
#525
0#
0+
#530
1#
1+
#535
0#
0+
#540
1#
1+
#545
0#
0+
#550
1#
1+
#555
0#
0+
#560
1#
1+
#565
0#
0+
#570
1#
1+
#575
0#
0+
#580
1#
1+
#585
0#
0+
#590
1#
1+
#595
0#
0$
0+
0,
b00000000 5
b00000000 6
b00000000 7
b00000000 8
#605
#615
#625
#635
#640
1$
1%
b01001101 &
b00001000 '
1,
1-
b01001101 .
b00001000 /
b01 4
b01001101 6
b00001000 8
#645
1#
1+
b01 3
b01001101 5
b01000101 6
b00001000 7
b00000001 :
#650
0#
0%
b00000000 &
b00000000 '
0+
0-
b00000000 .
b00000000 /
#655
1#
1+
b01000101 5
b00111101 6
b00000001 9
b00000010 :
#660
0#
0+
#665
1#
1+
b00111101 5
b00110101 6
b00000010 9
b00000011 :
#670
0#
0+
#675
1#
1+
b00110101 5
b00101101 6
b00000011 9
b00000100 :
#680
0#
0+
#685
1#
1+
b00101101 5
b00100101 6
b00000100 9
b00000101 :
#690
0#
0+
#695
1#
1+
b00100101 5
b00011101 6
b00000101 9
b00000110 :
#700
0#
0+
#705
1#
1+
b00011101 5
b00010101 6
b00000110 9
b00000111 :
#710
0#
0+
#715
1#
1+
b00010101 5
b00001101 6
b00000111 9
b00001000 :
#720
0#
0+
#725
1#
1+
b00001101 5
b00000101 6
b00001000 9
b00001001 :
#730
0#
0+
#735
1#
1+
b10 4
b00000101 5
b00001001 9
#740
0#
0+
#745
1#
1(
b00001001 )
b00000101 *
1+
10
b00001001 1
b00000101 2
b10 3
b00 4
#750
0#
0+
#755
1#
0(
b00000000 )
b00000000 *
1+
00
b00000000 1
b00000000 2
b00 3
b00000000 :
#760
0#
0+
#765
1#
1+
b00000000 9
#770
0#
0+
#775
1#
1+
#780
0#
0+
#785
1#
1+
#790
0#
0+
#795
1#
1+
#800
0#
0+
#805
1#
1+
#810
0#
0+
#815
1#
1+
#820
0#
0+
#825
1#
1+
#830
0#
0+
#835
1#
1+
#840
0#
0+
#845
1#
1+
#850
0#
0$
0+
0,
b00000000 5
b00000000 6
b00000000 7
b00000000 8
#860
#870
#880
#890
#895
1$
1%
b01111111 &
b00000001 '
1,
1-
b01111111 .
b00000001 /
b01 4
b01111111 6
b00000001 8
#900
1#
1+
b01 3
b01111111 5
b01111110 6
b00000001 7
b00000001 :
#905
0#
0%
b00000000 &
b00000000 '
0+
0-
b00000000 .
b00000000 /
#910
1#
1+
b01111110 5
b01111101 6
b00000001 9
b00000010 :
#915
0#
0+
#920
1#
1+
b01111101 5
b01111100 6
b00000010 9
b00000011 :
#925
0#
0+
#930
1#
1+
b01111100 5
b01111011 6
b00000011 9
b00000100 :
#935
0#
0+
#940
1#
1+
b01111011 5
b01111010 6
b00000100 9
b00000101 :
#945
0#
0+
#950
1#
1+
b01111010 5
b01111001 6
b00000101 9
b00000110 :
#955
0#
0+
#960
1#
1+
b01111001 5
b01111000 6
b00000110 9
b00000111 :
#965
0#
0+
#970
1#
1+
b01111000 5
b01110111 6
b00000111 9
b00001000 :
#975
0#
0+
#980
1#
1+
b01110111 5
b01110110 6
b00001000 9
b00001001 :
#985
0#
0+
#990
1#
1+
b01110110 5
b01110101 6
b00001001 9
b00001010 :
#995
0#
0+
#1000
1#
1+
b01110101 5
b01110100 6
b00001010 9
b00001011 :
#1005
0#
0+
#1010
1#
1+
b01110100 5
b01110011 6
b00001011 9
b00001100 :
#1015
0#
0+
#1020
1#
1+
b01110011 5
b01110010 6
b00001100 9
b00001101 :
#1025
0#
0+
#1030
1#
1+
b01110010 5
b01110001 6
b00001101 9
b00001110 :
#1035
0#
0+
#1040
1#
1+
b01110001 5
b01110000 6
b00001110 9
b00001111 :
#1045
0#
0+
#1050
1#
1+
b01110000 5
b01101111 6
b00001111 9
b00010000 :
#1055
0#
0+
#1060
1#
1+
b01101111 5
b01101110 6
b00010000 9
b00010001 :
#1065
0#
0+
#1070
1#
1+
b01101110 5
b01101101 6
b00010001 9
b00010010 :
#1075
0#
0+
#1080
1#
1+
b01101101 5
b01101100 6
b00010010 9
b00010011 :
#1085
0#
0+
#1090
1#
1+
b01101100 5
b01101011 6
b00010011 9
b00010100 :
#1095
0#
0+
#1100
1#
1+
b01101011 5
b01101010 6
b00010100 9
b00010101 :
#1105
0#
0+
#1110
1#
1+
b01101010 5
b01101001 6
b00010101 9
b00010110 :
#1115
0#
0+
#1120
1#
1+
b01101001 5
b01101000 6
b00010110 9
b00010111 :
#1125
0#
0+
#1130
1#
1+
b01101000 5
b01100111 6
b00010111 9
b00011000 :
#1135
0#
0+
#1140
1#
1+
b01100111 5
b01100110 6
b00011000 9
b00011001 :
#1145
0#
0+
#1150
1#
1+
b01100110 5
b01100101 6
b00011001 9
b00011010 :
#1155
0#
0+
#1160
1#
1+
b01100101 5
b01100100 6
b00011010 9
b00011011 :
#1165
0#
0+
#1170
1#
1+
b01100100 5
b01100011 6
b00011011 9
b00011100 :
#1175
0#
0+
#1180
1#
1+
b01100011 5
b01100010 6
b00011100 9
b00011101 :
#1185
0#
0+
#1190
1#
1+
b01100010 5
b01100001 6
b00011101 9
b00011110 :
#1195
0#
0+
#1200
1#
1+
b01100001 5
b01100000 6
b00011110 9
b00011111 :
#1205
0#
0+
#1210
1#
1+
b01100000 5
b01011111 6
b00011111 9
b00100000 :
#1215
0#
0+
#1220
1#
1+
b01011111 5
b01011110 6
b00100000 9
b00100001 :
#1225
0#
0+
#1230
1#
1+
b01011110 5
b01011101 6
b00100001 9
b00100010 :
#1235
0#
0+
#1240
1#
1+
b01011101 5
b01011100 6
b00100010 9
b00100011 :
#1245
0#
0+
#1250
1#
1+
b01011100 5
b01011011 6
b00100011 9
b00100100 :
#1255
0#
0+
#1260
1#
1+
b01011011 5
b01011010 6
b00100100 9
b00100101 :
#1265
0#
0+
#1270
1#
1+
b01011010 5
b01011001 6
b00100101 9
b00100110 :
#1275
0#
0+
#1280
1#
1+
b01011001 5
b01011000 6
b00100110 9
b00100111 :
#1285
0#
0+
#1290
1#
1+
b01011000 5
b01010111 6
b00100111 9
b00101000 :
#1295
0#
0+
#1300
1#
1+
b01010111 5
b01010110 6
b00101000 9
b00101001 :
#1305
0#
0+
#1310
1#
1+
b01010110 5
b01010101 6
b00101001 9
b00101010 :
#1315
0#
0+
#1320
1#
1+
b01010101 5
b01010100 6
b00101010 9
b00101011 :
#1325
0#
0+
#1330
1#
1+
b01010100 5
b01010011 6
b00101011 9
b00101100 :
#1335
0#
0+
#1340
1#
1+
b01010011 5
b01010010 6
b00101100 9
b00101101 :
#1345
0#
0+
#1350
1#
1+
b01010010 5
b01010001 6
b00101101 9
b00101110 :
#1355
0#
0+
#1360
1#
1+
b01010001 5
b01010000 6
b00101110 9
b00101111 :
#1365
0#
0+
#1370
1#
1+
b01010000 5
b01001111 6
b00101111 9
b00110000 :
#1375
0#
0+
#1380
1#
1+
b01001111 5
b01001110 6
b00110000 9
b00110001 :
#1385
0#
0+
#1390
1#
1+
b01001110 5
b01001101 6
b00110001 9
b00110010 :
#1395
0#
0+
#1400
1#
1+
b01001101 5
b01001100 6
b00110010 9
b00110011 :
#1405
0#
0+
#1410
1#
1+
b01001100 5
b01001011 6
b00110011 9
b00110100 :
#1415
0#
0+
#1420
1#
1+
b01001011 5
b01001010 6
b00110100 9
b00110101 :
#1425
0#
0+
#1430
1#
1+
b01001010 5
b01001001 6
b00110101 9
b00110110 :
#1435
0#
0+
#1440
1#
1+
b01001001 5
b01001000 6
b00110110 9
b00110111 :
#1445
0#
0+
#1450
1#
1+
b01001000 5
b01000111 6
b00110111 9
b00111000 :
#1455
0#
0+
#1460
1#
1+
b01000111 5
b01000110 6
b00111000 9
b00111001 :
#1465
0#
0+
#1470
1#
1+
b01000110 5
b01000101 6
b00111001 9
b00111010 :
#1475
0#
0+
#1480
1#
1+
b01000101 5
b01000100 6
b00111010 9
b00111011 :
#1485
0#
0+
#1490
1#
1+
b01000100 5
b01000011 6
b00111011 9
b00111100 :
#1495
0#
0+
#1500
1#
1+
b01000011 5
b01000010 6
b00111100 9
b00111101 :
#1505
0#
0+
#1510
1#
1+
b01000010 5
b01000001 6
b00111101 9
b00111110 :
#1515
0#
0+
#1520
1#
1+
b01000001 5
b01000000 6
b00111110 9
b00111111 :
#1525
0#
0+
#1530
1#
1+
b01000000 5
b00111111 6
b00111111 9
b01000000 :
#1535
0#
0+
#1540
1#
1+
b00111111 5
b00111110 6
b01000000 9
b01000001 :
#1545
0#
0+
#1550
1#
1+
b00111110 5
b00111101 6
b01000001 9
b01000010 :
#1555
0#
0+
#1560
1#
1+
b00111101 5
b00111100 6
b01000010 9
b01000011 :
#1565
0#
0+
#1570
1#
1+
b00111100 5
b00111011 6
b01000011 9
b01000100 :
#1575
0#
0+
#1580
1#
1+
b00111011 5
b00111010 6
b01000100 9
b01000101 :
#1585
0#
0+
#1590
1#
1+
b00111010 5
b00111001 6
b01000101 9
b01000110 :
#1595
0#
0+
#1600
1#
1+
b00111001 5
b00111000 6
b01000110 9
b01000111 :
#1605
0#
0+
#1610
1#
1+
b00111000 5
b00110111 6
b01000111 9
b01001000 :
#1615
0#
0+
#1620
1#
1+
b00110111 5
b00110110 6
b01001000 9
b01001001 :
#1625
0#
0+
#1630
1#
1+
b00110110 5
b00110101 6
b01001001 9
b01001010 :
#1635
0#
0+
#1640
1#
1+
b00110101 5
b00110100 6
b01001010 9
b01001011 :
#1645
0#
0+
#1650
1#
1+
b00110100 5
b00110011 6
b01001011 9
b01001100 :
#1655
0#
0+
#1660
1#
1+
b00110011 5
b00110010 6
b01001100 9
b01001101 :
#1665
0#
0+
#1670
1#
1+
b00110010 5
b00110001 6
b01001101 9
b01001110 :
#1675
0#
0+
#1680
1#
1+
b00110001 5
b00110000 6
b01001110 9
b01001111 :
#1685
0#
0+
#1690
1#
1+
b00110000 5
b00101111 6
b01001111 9
b01010000 :
#1695
0#
0+
#1700
1#
1+
b00101111 5
b00101110 6
b01010000 9
b01010001 :
#1705
0#
0+
#1710
1#
1+
b00101110 5
b00101101 6
b01010001 9
b01010010 :
#1715
0#
0+
#1720
1#
1+
b00101101 5
b00101100 6
b01010010 9
b01010011 :
#1725
0#
0+
#1730
1#
1+
b00101100 5
b00101011 6
b01010011 9
b01010100 :
#1735
0#
0+
#1740
1#
1+
b00101011 5
b00101010 6
b01010100 9
b01010101 :
#1745
0#
0+
#1750
1#
1+
b00101010 5
b00101001 6
b01010101 9
b01010110 :
#1755
0#
0+
#1760
1#
1+
b00101001 5
b00101000 6
b01010110 9
b01010111 :
#1765
0#
0+
#1770
1#
1+
b00101000 5
b00100111 6
b01010111 9
b01011000 :
#1775
0#
0+
#1780
1#
1+
b00100111 5
b00100110 6
b01011000 9
b01011001 :
#1785
0#
0+
#1790
1#
1+
b00100110 5
b00100101 6
b01011001 9
b01011010 :
#1795
0#
0+
#1800
1#
1+
b00100101 5
b00100100 6
b01011010 9
b01011011 :
#1805
0#
0+
#1810
1#
1+
b00100100 5
b00100011 6
b01011011 9
b01011100 :
#1815
0#
0+
#1820
1#
1+
b00100011 5
b00100010 6
b01011100 9
b01011101 :
#1825
0#
0+
#1830
1#
1+
b00100010 5
b00100001 6
b01011101 9
b01011110 :
#1835
0#
0+
#1840
1#
1+
b00100001 5
b00100000 6
b01011110 9
b01011111 :
#1845
0#
0+
#1850
1#
1+
b00100000 5
b00011111 6
b01011111 9
b01100000 :
#1855
0#
0+
#1860
1#
1+
b00011111 5
b00011110 6
b01100000 9
b01100001 :
#1865
0#
0+
#1870
1#
1+
b00011110 5
b00011101 6
b01100001 9
b01100010 :
#1875
0#
0+
#1880
1#
1+
b00011101 5
b00011100 6
b01100010 9
b01100011 :
#1885
0#
0+
#1890
1#
1+
b00011100 5
b00011011 6
b01100011 9
b01100100 :
#1895
0#
0+
#1900
1#
1+
b00011011 5
b00011010 6
b01100100 9
b01100101 :
#1905
0#
0+
#1910
1#
1+
b00011010 5
b00011001 6
b01100101 9
b01100110 :
#1915
0#
0+
#1920
1#
1+
b00011001 5
b00011000 6
b01100110 9
b01100111 :
#1925
0#
0+
#1930
1#
1+
b00011000 5
b00010111 6
b01100111 9
b01101000 :
#1935
0#
0+
#1940
1#
1+
b00010111 5
b00010110 6
b01101000 9
b01101001 :
#1945
0#
0+
#1950
1#
1+
b00010110 5
b00010101 6
b01101001 9
b01101010 :
#1955
0#
0+
#1960
1#
1+
b00010101 5
b00010100 6
b01101010 9
b01101011 :
#1965
0#
0+
#1970
1#
1+
b00010100 5
b00010011 6
b01101011 9
b01101100 :
#1975
0#
0+
#1980
1#
1+
b00010011 5
b00010010 6
b01101100 9
b01101101 :
#1985
0#
0+
#1990
1#
1+
b00010010 5
b00010001 6
b01101101 9
b01101110 :
#1995
0#
0+
#2000
1#
1+
b00010001 5
b00010000 6
b01101110 9
b01101111 :
#2005
0#
0+
#2010
1#
1+
b00010000 5
b00001111 6
b01101111 9
b01110000 :
#2015
0#
0+
#2020
1#
1+
b00001111 5
b00001110 6
b01110000 9
b01110001 :
#2025
0#
0+
#2030
1#
1+
b00001110 5
b00001101 6
b01110001 9
b01110010 :
#2035
0#
0+
#2040
1#
1+
b00001101 5
b00001100 6
b01110010 9
b01110011 :
#2045
0#
0+
#2050
1#
1+
b00001100 5
b00001011 6
b01110011 9
b01110100 :
#2055
0#
0+
#2060
1#
1+
b00001011 5
b00001010 6
b01110100 9
b01110101 :
#2065
0#
0+
#2070
1#
1+
b00001010 5
b00001001 6
b01110101 9
b01110110 :
#2075
0#
0+
#2080
1#
1+
b00001001 5
b00001000 6
b01110110 9
b01110111 :
#2085
0#
0+
#2090
1#
1+
b00001000 5
b00000111 6
b01110111 9
b01111000 :
#2095
0#
0+
#2100
1#
1+
b00000111 5
b00000110 6
b01111000 9
b01111001 :
#2105
0#
0+
#2110
1#
1+
b00000110 5
b00000101 6
b01111001 9
b01111010 :
#2115
0#
0+
#2120
1#
1+
b00000101 5
b00000100 6
b01111010 9
b01111011 :
#2125
0#
0+
#2130
1#
1+
b00000100 5
b00000011 6
b01111011 9
b01111100 :
#2135
0#
0+
#2140
1#
1+
b00000011 5
b00000010 6
b01111100 9
b01111101 :
#2145
0#
0+
#2150
1#
1+
b00000010 5
b00000001 6
b01111101 9
b01111110 :
#2155
0#
0+
#2160
1#
1+
b00000001 5
b00000000 6
b01111110 9
b01111111 :
#2165
0#
0+
#2170
1#
1+
b10 4
b00000000 5
b01111111 9
#2175
0#
0+
#2180
1#
1(
b01111111 )
1+
10
b01111111 1
b10 3
b00 4
#2185
0#
0+
#2190
1#
0(
b00000000 )
1+
00
b00000000 1
b00 3
b00000000 :
#2195
0#
0+
#2200
1#
1+
b00000000 9
#2205
0#
0+
#2210
1#
1+
#2215
0#
0+
#2220
1#
1+
#2225
0#
0+
#2230
1#
1+
#2235
0#
0+
#2240
1#
1+
#2245
0#
0+
#2250
1#
1+
#2255
0#
0+
#2260
1#
1+
#2265
0#
0+
#2270
1#
1+
#2275
0#
0+
#2280
1#
1+
#2285
0#
0$
0+
0,
b00000000 7
b00000000 8
#2295
#2305
#2315
#2325
#2330
1$
1%
b00001001 '
1,
1-
b00001001 /
b01 4
b00001001 8
#2335
1#
1+
b01 3
b10 4
b00001001 7
#2340
0#
0%
b00000000 '
0+
0-
b00000000 /
#2345
1#
1(
1+
10
b10 3
b00 4
#2350
0#
0+
#2355
1#
0(
1+
00
b00 3
#2360
0#
0+
#2365
1#
1+
#2370
0#
0+
#2375
1#
1+
#2380
0#
0+
#2385
1#
1+
#2390
0#
0+
#2395
1#
1+
#2400
0#
0+
#2405
1#
1+
#2410
0#
0+
#2415
1#
1+
#2420
0#
0+
#2425
1#
1+
#2430
0#
0+
#2435
1#
1+
#2440
0#
0+
#2445
1#
1+
#2450
0#
0$
0+
0,
b00000000 7
b00000000 8
