labs_backup/backup_lab08/lab08/ex_sorter/design_src/sorter.v
module sorter (
    input  [3:0] v0, v1, v2, v3,
    output [3:0] o0, o1, o2, o3
);
    wire [3:0] c0_min, c0_max, c1_min, c1_max, c2_min,
               c3_min, c3_max, c4_min;

    cmp c0 (.a(v0), .b(v1), .min(c0_min), .max(c0_max));
    cmp c1 (.a(c0_max), .b(v2), .min(c1_min), .max(c1_max));
    cmp c2 (.a(c1_max), .b(v3), .min(c2_min), .max(o3));

    cmp c3 (.a(c0_min), .b(c1_min), .min(c3_min), .max(c3_max));
    cmp c4 (.a(c3_max), .b(c2_min), .min(c4_min), .max(o2));

    cmp c5 (.a(c3_min), .b(c4_min), .min(o0), .max(o1));
endmodule


module cmp (
    input  unsigned [3:0] a,
    input  unsigned [3:0] b,
    output reg [3:0] max,
    output reg [3:0] min
);
    always @(*) begin
        max = (a > b) ? a : b;
        min = (a > b) ? b : a;
    end
endmodule

labs_backup/backup_lab08/lab08/ex_sorter/golden/golden_wave.vcd
$version Generated by VerilatedVcd $end
$timescale 1ps $end
 $scope module TOP $end
  $var wire 4 # v0 [3:0] $end
  $var wire 4 $ v1 [3:0] $end
  $var wire 4 % v2 [3:0] $end
  $var wire 4 & v3 [3:0] $end
  $var wire 4 ' o0 [3:0] $end
  $var wire 4 ( o1 [3:0] $end
  $var wire 4 ) o2 [3:0] $end
  $var wire 4 * o3 [3:0] $end
  $scope module sorter $end
   $var wire 4 + v0 [3:0] $end
   $var wire 4 , v1 [3:0] $end
   $var wire 4 - v2 [3:0] $end
   $var wire 4 . v3 [3:0] $end
   $var wire 4 / o0 [3:0] $end
   $var wire 4 0 o1 [3:0] $end
   $var wire 4 1 o2 [3:0] $end
   $var wire 4 2 o3 [3:0] $end
   $var wire 4 3 c0_min [3:0] $end
   $var wire 4 4 c0_max [3:0] $end
   $var wire 4 5 c1_min [3:0] $end
   $var wire 4 6 c1_max [3:0] $end
   $var wire 4 7 c2_min [3:0] $end
   $var wire 4 8 c3_min [3:0] $end
   $var wire 4 9 c3_max [3:0] $end
   $var wire 4 : c4_min [3:0] $end
   $scope module c0 $end
    $var wire 4 ; a [3:0] $end
    $var wire 4 < b [3:0] $end
    $var wire 4 = max [3:0] $end
    $var wire 4 > min [3:0] $end
   $upscope $end
   $scope module c1 $end
    $var wire 4 ? a [3:0] $end
    $var wire 4 @ b [3:0] $end
    $var wire 4 A max [3:0] $end
    $var wire 4 B min [3:0] $end
   $upscope $end
   $scope module c2 $end
    $var wire 4 C a [3:0] $end
    $var wire 4 D b [3:0] $end
    $var wire 4 E max [3:0] $end
    $var wire 4 F min [3:0] $end
   $upscope $end
   $scope module c3 $end
    $var wire 4 G a [3:0] $end
    $var wire 4 H b [3:0] $end
    $var wire 4 I max [3:0] $end
    $var wire 4 J min [3:0] $end
   $upscope $end
   $scope module c4 $end
    $var wire 4 K a [3:0] $end
    $var wire 4 L b [3:0] $end
    $var wire 4 M max [3:0] $end
    $var wire 4 N min [3:0] $end
   $upscope $end
   $scope module c5 $end
    $var wire 4 O a [3:0] $end
    $var wire 4 P b [3:0] $end
    $var wire 4 Q max [3:0] $end
    $var wire 4 R min [3:0] $end
   $upscope $end
  $upscope $end
 $upscope $end
$enddefinitions $end


#0
b0111 #
b0000 $
b0110 %
b1000 &
b0000 '
b0110 (
b0111 )
b1000 *
b0111 +
b0000 ,
b0110 -
b1000 .
b0000 /
b0110 0
b0111 1
b1000 2
b0000 3
b0111 4
b0110 5
b0111 6
b0111 7
b0000 8
b0110 9
b0110 :
b0111 ;
b0000 <
b0111 =
b0000 >
b0111 ?
b0110 @
b0111 A
b0110 B
b0111 C
b1000 D
b1000 E
b0111 F
b0000 G
b0110 H
b0110 I
b0000 J
b0110 K
b0111 L
b0111 M
b0110 N
b0000 O
b0110 P
b0110 Q
b0000 R
#10
b0011 #
b1010 $
b0100 %
b0001 &
b0001 '
b0011 (
b0100 )
b1010 *
b0011 +
b1010 ,
b0100 -
b0001 .
b0001 /
b0011 0
b0100 1
b1010 2
b0011 3
b1010 4
b0100 5
b1010 6
b0001 7
b0011 8
b0100 9
b0001 :
b0011 ;
b1010 <
b1010 =
b0011 >
b1010 ?
b0100 @
b1010 A
b0100 B
b1010 C
b0001 D
b1010 E
b0001 F
b0011 G
b0100 H
b0100 I
b0011 J
b0100 K
b0001 L
b0100 M
b0001 N
b0011 O
b0001 P
b0011 Q
b0001 R
#20
b0101 #
b1100 $
b0101 %
b1000 &
b0101 '
b0101 (
b1000 )
b1100 *
b0101 +
b1100 ,
b0101 -
b1000 .
b0101 /
b0101 0
b1000 1
b1100 2
b0101 3
b1100 4
b0101 5
b1100 6
b1000 7
b0101 8
b0101 9
b0101 :
b0101 ;
b1100 <
b1100 =
b0101 >
b1100 ?
b0101 @
b1100 A
b0101 B
b1100 C
b1000 D
b1100 E
b1000 F
b0101 G
b0101 H
b0101 I
b0101 J
b0101 K
b1000 L
b1000 M
b0101 N
b0101 O
b0101 P
b0101 Q
b0101 R
#30
b1110 #
b0110 %
b1110 &
b0110 '
b1100 (
b1110 )
b1110 *
b1110 +
b0110 -
b1110 .
b0110 /
b1100 0
b1110 1
b1110 2
b1100 3
b1110 4
b0110 5
b1110 6
b1110 7
b0110 8
b1100 9
b1100 :
b1110 ;
b1110 =
b1100 >
b1110 ?
b0110 @
b1110 A
b0110 B
b1110 C
b1110 D
b1110 E
b1110 F
b1100 G
b0110 H
b1100 I
b0110 J
b1100 K
b1110 L
b1110 M
b1100 N
b0110 O
b1100 P
b1100 Q
b0110 R
#40
b1111 #
b1111 $
b1010 %
b0000 &
b0000 '
b1010 (
b1111 )
b1111 *
b1111 +
b1111 ,
b1010 -
b0000 .
b0000 /
b1010 0
b1111 1
b1111 2
b1111 3
b1111 4
b1010 5
b1111 6
b0000 7
b1010 8
b1111 9
b0000 :
b1111 ;
b1111 <
b1111 =
b1111 >
b1111 ?
b1010 @
b1111 A
b1010 B
b1111 C
b0000 D
b1111 E
b0000 F
b1111 G
b1010 H
b1111 I
b1010 J
b1111 K
b0000 L
b1111 M
b0000 N
b1010 O
b0000 P
b1010 Q
b0000 R
#50
b1101 #
b1011 $
b0010 %
b0101 &
b0010 '
b0101 (
b1011 )
b1101 *
b1101 +
b1011 ,
b0010 -
b0101 .
b0010 /
b0101 0
b1011 1
b1101 2
b1011 3
b1101 4
b0010 5
b1101 6
b0101 7
b0010 8
b1011 9
b0101 :
b1101 ;
b1011 <
b1101 =
b1011 >
b1101 ?
b0010 @
b1101 A
b0010 B
b1101 C
b0101 D
b1101 E
b0101 F
b1011 G
b0010 H
b1011 I
b0010 J
b1011 K
b0101 L
b1011 M
b0101 N
b0010 O
b0101 P
b0101 Q
b0010 R
#60
b0011 #
b1101 $
b0110 %
b0100 &
b0011 '
b0100 (
b0110 )
b0011 +
b1101 ,
b0110 -
b0100 .
b0011 /
b0100 0
b0110 1
b0011 3
b0110 5
b0100 7
b0011 8
b0110 9
b0100 :
b0011 ;
b1101 <
b0011 >
b0110 @
b0110 B
b0100 D
b0100 F
b0011 G
b0110 H
b0110 I
b0011 J
b0110 K
b0100 L
b0110 M
b0100 N
b0011 O
b0100 P
b0100 Q
b0011 R
#70
b0001 #
b0101 $
b0001 %
b0101 &
b0001 '
b0001 (
b0101 )
b0101 *
b0001 +
b0101 ,
b0001 -
b0101 .
b0001 /
b0001 0
b0101 1
b0101 2
b0001 3
b0101 4
b0001 5
b0101 6
b0101 7
b0001 8
b0001 9
b0001 :
b0001 ;
b0101 <
b0101 =
b0001 >
b0101 ?
b0001 @
b0101 A
b0001 B
b0101 C
b0101 D
b0101 E
b0101 F
b0001 G
b0001 H
b0001 I
b0001 J
b0001 K
b0101 L
b0101 M
b0001 N
b0001 O
b0001 P
b0001 Q
b0001 R
#80
b1011 #
b0100 $
b1100 %
b0100 &
b0100 '
b0100 (
b1011 )
b1100 *
b1011 +
b0100 ,
b1100 -
b0100 .
b0100 /
b0100 0
b1011 1
b1100 2
b0100 3
b1011 4
b1011 5
b1100 6
b0100 7
b0100 8
b1011 9
b0100 :
b1011 ;
b0100 <
b1011 =
b0100 >
b1011 ?
b1100 @
b1100 A
b1011 B
b1100 C
b0100 D
b1100 E
b0100 F
b0100 G
b1011 H
b1011 I
b0100 J
b1011 K
b0100 L
b1011 M
b0100 N
b0100 O
b0100 P
b0100 Q
b0100 R
#90
b0010 #
b1100 $
b1000 %
b1111 &
b0010 '
b1000 (
b1100 )
b1111 *
b0010 +
b1100 ,
b1000 -
b1111 .
b0010 /
b1000 0
b1100 1
b1111 2
b0010 3
b1100 4
b1000 5
b1100 7
b0010 8
b1000 9
b1000 :
b0010 ;
b1100 <
b1100 =
b0010 >
b1100 ?
b1000 @
b1000 B
b1111 D
b1111 E
b1100 F
b0010 G
b1000 H
b1000 I
b0010 J
b1000 K
b1100 L
b1100 M
b1000 N
b0010 O
b1000 P
b1000 Q
b0010 R
#100
b0000 #
b0000 $
b0000 %
b0000 &
b0000 '
b0000 (
b0000 )
b0000 *
b0000 +
b0000 ,
b0000 -
b0000 .
b0000 /
b0000 0
b0000 1
b0000 2
b0000 3
b0000 4
b0000 5
b0000 6
b0000 7
b0000 8
b0000 9
b0000 :
b0000 ;
b0000 <
b0000 =
b0000 >
b0000 ?
b0000 @
b0000 A
b0000 B
b0000 C
b0000 D
b0000 E
b0000 F
b0000 G
b0000 H
b0000 I
b0000 J
b0000 K
b0000 L
b0000 M
b0000 N
b0000 O
b0000 P
b0000 Q
b0000 R
#110
b1111 #
b1111 $
b1111 %
b1111 &
b1111 '
b1111 (
b1111 )
b1111 *
b1111 +
b1111 ,
b1111 -
b1111 .
b1111 /
b1111 0
b1111 1
b1111 2
b1111 3
b1111 4
b1111 5
b1111 6
b1111 7
b1111 8
b1111 9
b1111 :
b1111 ;
b1111 <
b1111 =
b1111 >
b1111 ?
b1111 @
b1111 A
b1111 B
b1111 C
b1111 D
b1111 E
b1111 F
b1111 G
b1111 H
b1111 I
b1111 J
b1111 K
b1111 L
b1111 M
b1111 N
b1111 O
b1111 P
b1111 Q
b1111 R
#120
b0000 #
b0000 %
b0000 '
b0000 (
b0000 +
b0000 -
b0000 /
b0000 0
b0000 3
b0000 5
b0000 8
b0000 9
b0000 :
b0000 ;
b0000 >
b0000 @
b0000 B
b0000 G
b0000 H
b0000 I
b0000 J
b0000 K
b0000 N
b0000 O
b0000 P
b0000 Q
b0000 R
#130
b1111 #
b0000 $
b1111 %
b0000 &
b1111 +
b0000 ,
b1111 -
b0000 .
b1111 5
b0000 7
b1111 9
b1111 ;
b0000 <
b1111 @
b1111 B
b0000 D
b0000 F
b1111 H
b1111 I
b1111 K
b0000 L
#140
b0000 #
b0001 $
b0010 %
b0011 &
b0001 (
b0010 )
b0011 *
b0000 +
b0001 ,
b0010 -
b0011 .
b0001 0
b0010 1
b0011 2
b0001 4
b0001 5
b0010 6
b0010 7
b0001 9
b0001 :
b0000 ;
b0001 <
b0001 =
b0001 ?
b0010 @
b0010 A
b0001 B
b0010 C
b0011 D
b0011 E
b0010 F
b0001 H
b0001 I
b0001 K
b0010 L
b0010 M
b0001 N
b0001 P
b0001 Q
#150
b0011 #
b0010 $
b0001 %
b0000 &
b0011 +
b0010 ,
b0001 -
b0000 .
b0010 3
b0011 4
b0011 6
b0000 7
b0001 8
b0010 9
b0000 :
b0011 ;
b0010 <
b0011 =
b0010 >
b0011 ?
b0001 @
b0011 A
b0011 C
b0000 D
b0000 F
b0010 G
b0010 I
b0001 J
b0010 K
b0000 L
b0000 N
b0001 O
b0000 P
#160
b0101 #
b0101 $
b0101 %
b0101 &
b0101 '
b0101 (
b0101 )
b0101 *
b0101 +
b0101 ,
b0101 -
b0101 .
b0101 /
b0101 0
b0101 1
b0101 2
b0101 3
b0101 4
b0101 5
b0101 6
b0101 7
b0101 8
b0101 9
b0101 :
b0101 ;
b0101 <
b0101 =
b0101 >
b0101 ?
b0101 @
b0101 A
b0101 B
b0101 C
b0101 D
b0101 E
b0101 F
b0101 G
b0101 H
b0101 I
b0101 J
b0101 K
b0101 L
b0101 M
b0101 N
b0101 O
b0101 P
b0101 Q
b0101 R
#170
b0001 #
b0001 $
b0010 %
b0010 &
b0001 '
b0001 (
b0010 )
b0010 *
b0001 +
b0001 ,
b0010 -
b0010 .
b0001 /
b0001 0
b0010 1
b0010 2
b0001 3
b0001 4
b0001 5
b0010 6
b0010 7
b0001 8
b0001 9
b0001 :
b0001 ;
b0001 <
b0001 =
b0001 >
b0001 ?
b0010 @
b0010 A
b0001 B
b0010 C
b0010 D
b0010 E
b0010 F
b0001 G
b0001 H
b0001 I
b0001 J
b0001 K
b0010 L
b0010 M
b0001 N
b0001 O
b0001 P
b0001 Q
b0001 R
#180
b0111 #
b1000 $
b1001 %
b1010 &
b0111 '
b1000 (
b1001 )
b1010 *
b0111 +
b1000 ,
b1001 -
b1010 .
b0111 /
b1000 0
b1001 1
b1010 2
b0111 3
b1000 4
b1000 5
b1001 6
b1001 7
b0111 8
b1000 9
b1000 :
b0111 ;
b1000 <
b1000 =
b0111 >
b1000 ?
b1001 @
b1001 A
b1000 B
b1001 C
b1010 D
b1010 E
b1001 F
b0111 G
b1000 H
b1000 I
b0111 J
b1000 K
b1001 L
b1001 M
b1000 N
b0111 O
b1000 P
b1000 Q
b0111 R
#190
b1110 #
b1101 $
b1100 %
b1011 &
b1011 '
b1100 (
b1101 )
b1110 *
b1110 +
b1101 ,
b1100 -
b1011 .
b1011 /
b1100 0
b1101 1
b1110 2
b1101 3
b1110 4
b1100 5
b1110 6
b1011 7
b1100 8
b1101 9
b1011 :
b1110 ;
b1101 <
b1110 =
b1101 >
b1110 ?
b1100 @
b1110 A
b1100 B
b1110 C
b1011 D
b1110 E
b1011 F
b1101 G
b1100 H
b1101 I
b1100 J
b1101 K
b1011 L
b1101 M
b1011 N
b1100 O
b1011 P
b1100 Q
b1011 R
