labs_backup/backup_lab05/ex_div/design_src/div.v
module div (
    input  [7:0] a,
    output reg [7:0] div2,
    output reg [7:0] div4,
    output reg [7:0] div8
);
    always @(*) begin
        // div2 = a >> 1;   // a / 2
        // div4 = a >> 2;   // a / 4
        // div8 = a >> 3;   // a / 8

        div2 = {1'b0, a[7:1]};   // a / 2
        div4 = {2'b0, a[7:2]};   // a / 4
        div8 = {3'b0, a[7:3]};   // a / 8
    end
endmodule

labs_backup/backup_lab05/ex_div/sim_result/wave.vcd
$version Generated by VerilatedVcd $end
$timescale 1ps $end
 $scope module TOP $end
  $var wire 8 # a [7:0] $end
  $var wire 8 $ div2 [7:0] $end
  $var wire 8 % div4 [7:0] $end
  $var wire 8 & div8 [7:0] $end
  $scope module div $end
   $var wire 8 ' a [7:0] $end
   $var wire 8 ( div2 [7:0] $end
   $var wire 8 ) div4 [7:0] $end
   $var wire 8 * div8 [7:0] $end
  $upscope $end
 $upscope $end
$enddefinitions $end


#0
b01101001 #
b00110100 $
b00011010 %
b00001101 &
b01101001 '
b00110100 (
b00011010 )
b00001101 *
#10
b01000000 #
b00100000 $
b00010000 %
b00001000 &
b01000000 '
b00100000 (
b00010000 )
b00001000 *
#20
b01101001 #
b00110100 $
b00011010 %
b00001101 &
b01101001 '
b00110100 (
b00011010 )
b00001101 *
#30
b10100011 #
b01010001 $
b00101000 %
b00010100 &
b10100011 '
b01010001 (
b00101000 )
b00010100 *
#40
b01100110 #
b00110011 $
b00011001 %
b00001100 &
b01100110 '
b00110011 (
b00011001 )
b00001100 *
#50
b10010111 #
b01001011 $
b00100101 %
b00010010 &
b10010111 '
b01001011 (
b00100101 )
b00010010 *
#60
b11110010 #
b01111001 $
b00111100 %
b00011110 &
b11110010 '
b01111001 (
b00111100 )
b00011110 *
#70
b11010000 #
b01101000 $
b00110100 %
b00011010 &
b11010000 '
b01101000 (
b00110100 )
b00011010 *
#80
b00110100 #
b00011010 $
b00001101 %
b00000110 &
b00110100 '
b00011010 (
b00001101 )
b00000110 *
#90
b10111101 #
b01011110 $
b00101111 %
b00010111 &
b10111101 '
b01011110 (
b00101111 )
b00010111 *
#100
b01101100 #
b00110110 $
b00011011 %
b00001101 &
b01101100 '
b00110110 (
b00011011 )
b00001101 *
#110
b01010100 #
b00101010 $
b00010101 %
b00001010 &
b01010100 '
b00101010 (
b00010101 )
b00001010 *
#120
b01000011 #
b00100001 $
b00010000 %
b00001000 &
b01000011 '
b00100001 (
b00010000 )
b00001000 *
#130
b01101011 #
b00110101 $
b00011010 %
b00001101 &
b01101011 '
b00110101 (
b00011010 )
b00001101 *
#140
b01001111 #
b00100111 $
b00010011 %
b00001001 &
b01001111 '
b00100111 (
b00010011 )
b00001001 *
#150
b11001010 #
b01100101 $
b00110010 %
b00011001 &
b11001010 '
b01100101 (
b00110010 )
b00011001 *
#160
b11010100 #
b01101010 $
b00110101 %
b00011010 &
b11010100 '
b01101010 (
b00110101 )
b00011010 *
#170
b10101011 #
b01010101 $
b00101010 %
b00010101 &
b10101011 '
b01010101 (
b00101010 )
b00010101 *
#180
b10011101 #
b01001110 $
b00100111 %
b00010011 &
b10011101 '
b01001110 (
b00100111 )
b00010011 *
#190
b01110101 #
b00111010 $
b00011101 %
b00001110 &
b01110101 '
b00111010 (
b00011101 )
b00001110 *
