labs_backup/backup_lab10/lab10/ex_mod/design_src/mod.v
module mod (
    input clk,
    input rst_n,
    input valid,
    input [7:0] dividend,
    input [7:0] divisor,
    output reg ready,
    output reg [7:0] remainder
);
    localparam IDLE = 0,
               BUSY = 1,
               OUT  = 2;
    
    reg [1:0] S, S_nxt;
    reg [7:0] a, a_nxt;
    reg [7:0] b, b_nxt;

    always @(*) begin
        case (S)
            IDLE: begin
                if (valid) begin
                    a_nxt = dividend;
                    b_nxt = divisor;
                    S_nxt = BUSY;
                end
                else begin
                    a_nxt = a;
                    b_nxt = b;
                    S_nxt = IDLE;
                end
            end
            BUSY: begin
                if (a < b) begin
                    a_nxt = a;
                    b_nxt = b;
                    S_nxt = OUT;
                end
                else begin
                    a_nxt = a - b;
                    b_nxt = b;
                    S_nxt = BUSY;
                end
            end
            OUT: begin
                a_nxt = a;
                b_nxt = b;
                S_nxt = IDLE;
            end
            default: begin
                a_nxt = 0;
                b_nxt = 0;
                S_nxt = IDLE;
            end
        endcase
    end

    always @(posedge clk, negedge rst_n) begin
        if (~rst_n) begin
            S <= IDLE;
            a <= 0;
            b <= 0;
        end
        else begin
            S <= S_nxt;
            a <= a_nxt;
            b <= b_nxt;
        end
    end

    always @(*) begin
        ready = S == OUT;
        remainder = S == OUT ? a : 0;
    end
endmodule

labs_backup/backup_lab10/ex_mod/golden/golden_wave.vcd
$version Generated by VerilatedVcd $end
$timescale 1ps $end
 $scope module TOP $end
  $var wire 1 # clk $end
  $var wire 1 $ rst_n $end
  $var wire 1 % valid $end
  $var wire 8 & dividend [7:0] $end
  $var wire 8 ' divisor [7:0] $end
  $var wire 1 ( ready $end
  $var wire 8 ) remainder [7:0] $end
  $scope module mod $end
   $var wire 1 * clk $end
   $var wire 1 + rst_n $end
   $var wire 1 , valid $end
   $var wire 8 - dividend [7:0] $end
   $var wire 8 . divisor [7:0] $end
   $var wire 1 / ready $end
   $var wire 8 0 remainder [7:0] $end
   $var wire 32 7 IDLE [31:0] $end
   $var wire 32 8 BUSY [31:0] $end
   $var wire 32 9 OUT [31:0] $end
   $var wire 2 1 S [1:0] $end
   $var wire 2 2 S_nxt [1:0] $end
   $var wire 8 3 a [7:0] $end
   $var wire 8 4 a_nxt [7:0] $end
   $var wire 8 5 b [7:0] $end
   $var wire 8 6 b_nxt [7:0] $end
  $upscope $end
 $upscope $end
$enddefinitions $end


#5
0#
0$
0%
b00000000 &
b00000000 '
0(
b00000000 )
0*
0+
0,
b00000000 -
b00000000 .
0/
b00000000 0
b00 1
b00 2
b00000000 3
b00000000 4
b00000000 5
b00000000 6
b00000000000000000000000000000000 7
b00000000000000000000000000000001 8
b00000000000000000000000000000010 9
#10
#15
#20
1#
1*
#25
0#
0*
#30
1#
1*
#35
0#
1$
0*
1+
#40
1#
1*
#45
0#
1%
b00001000 &
b00000010 '
0*
1,
b00001000 -
b00000010 .
b01 2
b00001000 4
b00000010 6
#50
1#
1*
b01 1
b00001000 3
b00000110 4
b00000010 5
#55
0#
0%
b00000000 &
b00000000 '
0*
0,
b00000000 -
b00000000 .
#60
1#
1*
b00000110 3
b00000100 4
#65
0#
0*
#70
1#
1*
b00000100 3
b00000010 4
#75
0#
0*
#80
1#
1*
b00000010 3
b00000000 4
#85
0#
0*
#90
1#
1*
b10 2
b00000000 3
#95
0#
0*
#100
1#
1(
1*
1/
b10 1
b00 2
#105
0#
0*
#110
1#
0(
1*
0/
b00 1
#115
0#
0*
#120
1#
1*
#125
0#
0*
#130
1#
1*
#135
0#
0*
#140
1#
1*
#145
0#
0*
#150
1#
1*
#155
0#
0*
#160
1#
1*
#165
0#
0*
#170
1#
1*
#175
0#
0*
#180
1#
1*
#185
0#
0*
#190
1#
1*
#195
0#
0*
#200
1#
1*
#205
0#
0$
0*
0+
b00000000 5
b00000000 6
#215
#225
#235
#245
#250
1$
1%
b00010011 &
b00000011 '
1+
1,
b00010011 -
b00000011 .
b01 2
b00010011 4
b00000011 6
#255
1#
1*
b01 1
b00010011 3
b00010000 4
b00000011 5
#260
0#
0%
b00000000 &
b00000000 '
0*
0,
b00000000 -
b00000000 .
#265
1#
1*
b00010000 3
b00001101 4
#270
0#
0*
#275
1#
1*
b00001101 3
b00001010 4
#280
0#
0*
#285
1#
1*
b00001010 3
b00000111 4
#290
0#
0*
#295
1#
1*
b00000111 3
b00000100 4
#300
0#
0*
#305
1#
1*
b00000100 3
b00000001 4
#310
0#
0*
#315
1#
1*
b10 2
b00000001 3
#320
0#
0*
#325
1#
1(
b00000001 )
1*
1/
b00000001 0
b10 1
b00 2
#330
0#
0*
#335
1#
0(
b00000000 )
1*
0/
b00000000 0
b00 1
#340
0#
0*
#345
1#
1*
#350
0#
0*
#355
1#
1*
#360
0#
0*
#365
1#
1*
#370
0#
0*
#375
1#
1*
#380
0#
0*
#385
1#
1*
#390
0#
0*
#395
1#
1*
#400
0#
0*
#405
1#
1*
#410
0#
0*
#415
1#
1*
#420
0#
0*
#425
1#
1*
#430
0#
0$
0*
0+
b00000000 3
b00000000 4
b00000000 5
b00000000 6
#440
#450
#460
#470
#475
1$
1%
b00000010 &
b00000101 '
1+
1,
b00000010 -
b00000101 .
b01 2
b00000010 4
b00000101 6
#480
1#
1*
b01 1
b10 2
b00000010 3
b00000101 5
#485
0#
0%
b00000000 &
b00000000 '
0*
0,
b00000000 -
b00000000 .
#490
1#
1(
b00000010 )
1*
1/
b00000010 0
b10 1
b00 2
#495
0#
0*
#500
1#
0(
b00000000 )
1*
0/
b00000000 0
b00 1
#505
0#
0*
#510
1#
1*
#515
0#
0*
#520
1#
1*
#525
0#
0*
#530
1#
1*
#535
0#
0*
#540
1#
1*
#545
0#
0*
#550
1#
1*
#555
0#
0*
#560
1#
1*
#565
0#
0*
#570
1#
1*
#575
0#
0*
#580
1#
1*
#585
0#
0*
#590
1#
1*
#595
0#
0$
0*
0+
b00000000 3
b00000000 4
b00000000 5
b00000000 6
#605
#615
#625
#635
#640
1$
1%
b01001101 &
b00001000 '
1+
1,
b01001101 -
b00001000 .
b01 2
b01001101 4
b00001000 6
#645
1#
1*
b01 1
b01001101 3
b01000101 4
b00001000 5
#650
0#
0%
b00000000 &
b00000000 '
0*
0,
b00000000 -
b00000000 .
#655
1#
1*
b01000101 3
b00111101 4
#660
0#
0*
#665
1#
1*
b00111101 3
b00110101 4
#670
0#
0*
#675
1#
1*
b00110101 3
b00101101 4
#680
0#
0*
#685
1#
1*
b00101101 3
b00100101 4
#690
0#
0*
#695
1#
1*
b00100101 3
b00011101 4
#700
0#
0*
#705
1#
1*
b00011101 3
b00010101 4
#710
0#
0*
#715
1#
1*
b00010101 3
b00001101 4
#720
0#
0*
#725
1#
1*
b00001101 3
b00000101 4
#730
0#
0*
#735
1#
1*
b10 2
b00000101 3
#740
0#
0*
#745
1#
1(
b00000101 )
1*
1/
b00000101 0
b10 1
b00 2
#750
0#
0*
#755
1#
0(
b00000000 )
1*
0/
b00000000 0
b00 1
#760
0#
0*
#765
1#
1*
#770
0#
0*
#775
1#
1*
#780
0#
0*
#785
1#
1*
#790
0#
0*
#795
1#
1*
#800
0#
0*
#805
1#
1*
#810
0#
0*
#815
1#
1*
#820
0#
0*
#825
1#
1*
#830
0#
0*
#835
1#
1*
#840
0#
0*
#845
1#
1*
#850
0#
0$
0*
0+
b00000000 3
b00000000 4
b00000000 5
b00000000 6
#860
#870
#880
#890
#895
1$
1%
b01111111 &
b00000001 '
1+
1,
b01111111 -
b00000001 .
b01 2
b01111111 4
b00000001 6
#900
1#
1*
b01 1
b01111111 3
b01111110 4
b00000001 5
#905
0#
0%
b00000000 &
b00000000 '
0*
0,
b00000000 -
b00000000 .
#910
1#
1*
b01111110 3
b01111101 4
#915
0#
0*
#920
1#
1*
b01111101 3
b01111100 4
#925
0#
0*
#930
1#
1*
b01111100 3
b01111011 4
#935
0#
0*
#940
1#
1*
b01111011 3
b01111010 4
#945
0#
0*
#950
1#
1*
b01111010 3
b01111001 4
#955
0#
0*
#960
1#
1*
b01111001 3
b01111000 4
#965
0#
0*
#970
1#
1*
b01111000 3
b01110111 4
#975
0#
0*
#980
1#
1*
b01110111 3
b01110110 4
#985
0#
0*
#990
1#
1*
b01110110 3
b01110101 4
#995
0#
0*
#1000
1#
1*
b01110101 3
b01110100 4
#1005
0#
0*
#1010
1#
1*
b01110100 3
b01110011 4
#1015
0#
0*
#1020
1#
1*
b01110011 3
b01110010 4
#1025
0#
0*
#1030
1#
1*
b01110010 3
b01110001 4
#1035
0#
0*
#1040
1#
1*
b01110001 3
b01110000 4
#1045
0#
0*
#1050
1#
1*
b01110000 3
b01101111 4
#1055
0#
0*
#1060
1#
1*
b01101111 3
b01101110 4
#1065
0#
0*
#1070
1#
1*
b01101110 3
b01101101 4
#1075
0#
0*
#1080
1#
1*
b01101101 3
b01101100 4
#1085
0#
0*
#1090
1#
1*
b01101100 3
b01101011 4
#1095
0#
0*
#1100
1#
1*
b01101011 3
b01101010 4
#1105
0#
0*
#1110
1#
1*
b01101010 3
b01101001 4
#1115
0#
0*
#1120
1#
1*
b01101001 3
b01101000 4
#1125
0#
0*
#1130
1#
1*
b01101000 3
b01100111 4
#1135
0#
0*
#1140
1#
1*
b01100111 3
b01100110 4
#1145
0#
0*
#1150
1#
1*
b01100110 3
b01100101 4
#1155
0#
0*
#1160
1#
1*
b01100101 3
b01100100 4
#1165
0#
0*
#1170
1#
1*
b01100100 3
b01100011 4
#1175
0#
0*
#1180
1#
1*
b01100011 3
b01100010 4
#1185
0#
0*
#1190
1#
1*
b01100010 3
b01100001 4
#1195
0#
0*
#1200
1#
1*
b01100001 3
b01100000 4
#1205
0#
0*
#1210
1#
1*
b01100000 3
b01011111 4
#1215
0#
0*
#1220
1#
1*
b01011111 3
b01011110 4
#1225
0#
0*
#1230
1#
1*
b01011110 3
b01011101 4
#1235
0#
0*
#1240
1#
1*
b01011101 3
b01011100 4
#1245
0#
0*
#1250
1#
1*
b01011100 3
b01011011 4
#1255
0#
0*
#1260
1#
1*
b01011011 3
b01011010 4
#1265
0#
0*
#1270
1#
1*
b01011010 3
b01011001 4
#1275
0#
0*
#1280
1#
1*
b01011001 3
b01011000 4
#1285
0#
0*
#1290
1#
1*
b01011000 3
b01010111 4
#1295
0#
0*
#1300
1#
1*
b01010111 3
b01010110 4
#1305
0#
0*
#1310
1#
1*
b01010110 3
b01010101 4
#1315
0#
0*
#1320
1#
1*
b01010101 3
b01010100 4
#1325
0#
0*
#1330
1#
1*
b01010100 3
b01010011 4
#1335
0#
0*
#1340
1#
1*
b01010011 3
b01010010 4
#1345
0#
0*
#1350
1#
1*
b01010010 3
b01010001 4
#1355
0#
0*
#1360
1#
1*
b01010001 3
b01010000 4
#1365
0#
0*
#1370
1#
1*
b01010000 3
b01001111 4
#1375
0#
0*
#1380
1#
1*
b01001111 3
b01001110 4
#1385
0#
0*
#1390
1#
1*
b01001110 3
b01001101 4
#1395
0#
0*
#1400
1#
1*
b01001101 3
b01001100 4
#1405
0#
0*
#1410
1#
1*
b01001100 3
b01001011 4
#1415
0#
0*
#1420
1#
1*
b01001011 3
b01001010 4
#1425
0#
0*
#1430
1#
1*
b01001010 3
b01001001 4
#1435
0#
0*
#1440
1#
1*
b01001001 3
b01001000 4
#1445
0#
0*
#1450
1#
1*
b01001000 3
b01000111 4
#1455
0#
0*
#1460
1#
1*
b01000111 3
b01000110 4
#1465
0#
0*
#1470
1#
1*
b01000110 3
b01000101 4
#1475
0#
0*
#1480
1#
1*
b01000101 3
b01000100 4
#1485
0#
0*
#1490
1#
1*
b01000100 3
b01000011 4
#1495
0#
0*
#1500
1#
1*
b01000011 3
b01000010 4
#1505
0#
0*
#1510
1#
1*
b01000010 3
b01000001 4
#1515
0#
0*
#1520
1#
1*
b01000001 3
b01000000 4
#1525
0#
0*
#1530
1#
1*
b01000000 3
b00111111 4
#1535
0#
0*
#1540
1#
1*
b00111111 3
b00111110 4
#1545
0#
0*
#1550
1#
1*
b00111110 3
b00111101 4
#1555
0#
0*
#1560
1#
1*
b00111101 3
b00111100 4
#1565
0#
0*
#1570
1#
1*
b00111100 3
b00111011 4
#1575
0#
0*
#1580
1#
1*
b00111011 3
b00111010 4
#1585
0#
0*
#1590
1#
1*
b00111010 3
b00111001 4
#1595
0#
0*
#1600
1#
1*
b00111001 3
b00111000 4
#1605
0#
0*
#1610
1#
1*
b00111000 3
b00110111 4
#1615
0#
0*
#1620
1#
1*
b00110111 3
b00110110 4
#1625
0#
0*
#1630
1#
1*
b00110110 3
b00110101 4
#1635
0#
0*
#1640
1#
1*
b00110101 3
b00110100 4
#1645
0#
0*
#1650
1#
1*
b00110100 3
b00110011 4
#1655
0#
0*
#1660
1#
1*
b00110011 3
b00110010 4
#1665
0#
0*
#1670
1#
1*
b00110010 3
b00110001 4
#1675
0#
0*
#1680
1#
1*
b00110001 3
b00110000 4
#1685
0#
0*
#1690
1#
1*
b00110000 3
b00101111 4
#1695
0#
0*
#1700
1#
1*
b00101111 3
b00101110 4
#1705
0#
0*
#1710
1#
1*
b00101110 3
b00101101 4
#1715
0#
0*
#1720
1#
1*
b00101101 3
b00101100 4
#1725
0#
0*
#1730
1#
1*
b00101100 3
b00101011 4
#1735
0#
0*
#1740
1#
1*
b00101011 3
b00101010 4
#1745
0#
0*
#1750
1#
1*
b00101010 3
b00101001 4
#1755
0#
0*
#1760
1#
1*
b00101001 3
b00101000 4
#1765
0#
0*
#1770
1#
1*
b00101000 3
b00100111 4
#1775
0#
0*
#1780
1#
1*
b00100111 3
b00100110 4
#1785
0#
0*
#1790
1#
1*
b00100110 3
b00100101 4
#1795
0#
0*
#1800
1#
1*
b00100101 3
b00100100 4
#1805
0#
0*
#1810
1#
1*
b00100100 3
b00100011 4
#1815
0#
0*
#1820
1#
1*
b00100011 3
b00100010 4
#1825
0#
0*
#1830
1#
1*
b00100010 3
b00100001 4
#1835
0#
0*
#1840
1#
1*
b00100001 3
b00100000 4
#1845
0#
0*
#1850
1#
1*
b00100000 3
b00011111 4
#1855
0#
0*
#1860
1#
1*
b00011111 3
b00011110 4
#1865
0#
0*
#1870
1#
1*
b00011110 3
b00011101 4
#1875
0#
0*
#1880
1#
1*
b00011101 3
b00011100 4
#1885
0#
0*
#1890
1#
1*
b00011100 3
b00011011 4
#1895
0#
0*
#1900
1#
1*
b00011011 3
b00011010 4
#1905
0#
0*
#1910
1#
1*
b00011010 3
b00011001 4
#1915
0#
0*
#1920
1#
1*
b00011001 3
b00011000 4
#1925
0#
0*
#1930
1#
1*
b00011000 3
b00010111 4
#1935
0#
0*
#1940
1#
1*
b00010111 3
b00010110 4
#1945
0#
0*
#1950
1#
1*
b00010110 3
b00010101 4
#1955
0#
0*
#1960
1#
1*
b00010101 3
b00010100 4
#1965
0#
0*
#1970
1#
1*
b00010100 3
b00010011 4
#1975
0#
0*
#1980
1#
1*
b00010011 3
b00010010 4
#1985
0#
0*
#1990
1#
1*
b00010010 3
b00010001 4
#1995
0#
0*
#2000
1#
1*
b00010001 3
b00010000 4
#2005
0#
0*
#2010
1#
1*
b00010000 3
b00001111 4
#2015
0#
0*
#2020
1#
1*
b00001111 3
b00001110 4
#2025
0#
0*
#2030
1#
1*
b00001110 3
b00001101 4
#2035
0#
0*
#2040
1#
1*
b00001101 3
b00001100 4
#2045
0#
0*
#2050
1#
1*
b00001100 3
b00001011 4
#2055
0#
0*
#2060
1#
1*
b00001011 3
b00001010 4
#2065
0#
0*
#2070
1#
1*
b00001010 3
b00001001 4
#2075
0#
0*
#2080
1#
1*
b00001001 3
b00001000 4
#2085
0#
0*
#2090
1#
1*
b00001000 3
b00000111 4
#2095
0#
0*
#2100
1#
1*
b00000111 3
b00000110 4
#2105
0#
0*
#2110
1#
1*
b00000110 3
b00000101 4
#2115
0#
0*
#2120
1#
1*
b00000101 3
b00000100 4
#2125
0#
0*
#2130
1#
1*
b00000100 3
b00000011 4
#2135
0#
0*
#2140
1#
1*
b00000011 3
b00000010 4
#2145
0#
0*
#2150
1#
1*
b00000010 3
b00000001 4
#2155
0#
0*
#2160
1#
1*
b00000001 3
b00000000 4
#2165
0#
0*
#2170
1#
1*
b10 2
b00000000 3
#2175
0#
0*
#2180
1#
1(
1*
1/
b10 1
b00 2
#2185
0#
0*
#2190
1#
0(
1*
0/
b00 1
#2195
0#
0*
#2200
1#
1*
#2205
0#
0*
#2210
1#
1*
#2215
0#
0*
#2220
1#
1*
#2225
0#
0*
#2230
1#
1*
#2235
0#
0*
#2240
1#
1*
#2245
0#
0*
#2250
1#
1*
#2255
0#
0*
#2260
1#
1*
#2265
0#
0*
#2270
1#
1*
#2275
0#
0*
#2280
1#
1*
#2285
0#
0$
0*
0+
b00000000 5
b00000000 6
#2295
#2305
#2315
#2325
#2330
1$
1%
b00001001 '
1+
1,
b00001001 .
b01 2
b00001001 6
#2335
1#
1*
b01 1
b10 2
b00001001 5
#2340
0#
0%
b00000000 '
0*
0,
b00000000 .
#2345
1#
1(
1*
1/
b10 1
b00 2
#2350
0#
0*
#2355
1#
0(
1*
0/
b00 1
#2360
0#
0*
#2365
1#
1*
#2370
0#
0*
#2375
1#
1*
#2380
0#
0*
#2385
1#
1*
#2390
0#
0*
#2395
1#
1*
#2400
0#
0*
#2405
1#
1*
#2410
0#
0*
#2415
1#
1*
#2420
0#
0*
#2425
1#
1*
#2430
0#
0*
#2435
1#
1*
#2440
0#
0*
#2445
1#
1*
#2450
0#
0$
0*
0+
b00000000 5
b00000000 6
