labs_backup/backup_lab03/lab03/ex_vandor/design_src/vandor.v
module vandor (
    input  [3:0] a,
    input  [3:0] b,
    output reg [3:0] and_ab,
    output reg [3:0] or_ab,
    output reg and_a,
    output reg or_a
);
    always @(*) begin
        and_ab = a & b;
        or_ab  = a | b;
        and_a  = a[3] & a[2] & a[1] & a[0]; // &a
        or_a   = |a;                        // Reduction OR
    end
endmodule

labs_backup/backup_lab03/ex_vandor/golden/golden_wave.vcd
$version Generated by VerilatedVcd $end
$timescale 1ps $end
 $scope module TOP $end
  $var wire 4 # a [3:0] $end
  $var wire 4 $ b [3:0] $end
  $var wire 4 % and_ab [3:0] $end
  $var wire 4 & or_ab [3:0] $end
  $var wire 1 ' and_a $end
  $var wire 1 ( or_a $end
  $scope module vandor $end
   $var wire 4 ) a [3:0] $end
   $var wire 4 * b [3:0] $end
   $var wire 4 + and_ab [3:0] $end
   $var wire 4 , or_ab [3:0] $end
   $var wire 1 - and_a $end
   $var wire 1 . or_a $end
  $upscope $end
 $upscope $end
$enddefinitions $end


#0
b0000 #
b0000 $
b0000 %
b0000 &
0'
0(
b0000 )
b0000 *
b0000 +
b0000 ,
0-
0.
#10
b0001 #
b0001 $
b0001 %
b0001 &
1(
b0001 )
b0001 *
b0001 +
b0001 ,
1.
#20
b0010 #
b0011 $
b0010 %
b0011 &
b0010 )
b0011 *
b0010 +
b0011 ,
#30
b0100 #
b1000 $
b0000 %
b1100 &
b0100 )
b1000 *
b0000 +
b1100 ,
#40
b0101 #
b1010 $
b1111 &
b0101 )
b1010 *
b1111 ,
#50
b0110 #
b1001 $
b0110 )
b1001 *
#60
b0111 #
b0111 $
b0111 %
b0111 &
b0111 )
b0111 *
b0111 +
b0111 ,
#70
b1100 #
b0011 $
b0000 %
b1111 &
b1100 )
b0011 *
b0000 +
b1111 ,
#80
b1111 #
b0000 $
1'
b1111 )
b0000 *
1-
#90
b1111 $
b1111 %
b1111 *
b1111 +
