labs_backup/backup_lab11/lab11/pr_fifo/design_src/fifo.v
module fifo (
    input clk,
    input rst_n,
    output reg       w_ready,
    input            w_valid,
    input      [7:0] w_data,
    output reg       r_ready,
    input            r_valid,
    output reg [7:0] r_data
);
    reg [7:0] R[0:7] /* verilator public */; /* the array */
    reg [7:0] R_nxt[0:7];
    reg [7:0] r_data_nxt;

    reg [3:0] wp, wp_nxt; /* the write pointer */
    reg [3:0] rp, rp_nxt; /* the read pointer */

    reg w_fire, r_fire;
    
    integer i;

    always @(*) begin
        w_fire = w_ready & w_valid;
        r_fire = r_ready & r_valid;
        for (i = 0; i < 8; i = i + 1) begin
            /* R_nxt assignment */
        end
        /* other _nxt assignment */
    end

    always @(posedge clk, negedge rst_n) begin
        if (~rst_n) begin
            for (i = 0; i < 8; i = i + 1) begin
                /* R initial state */
            end
            /* other register initial state */
        end
        else begin
            for (i = 0; i < 8; i = i + 1) begin
                /* R <= ??*/
            end
            /* other register */
        end
    end

    always @(*) begin
        /* output signals assignment */
    end
endmodule

labs_backup/backup_lab11/lab11/pr_fifo/golden/golden_wave.vcd
$version Generated by VerilatedVcd $end
$timescale 1ps $end
 $scope module TOP $end
  $scope module fifo $end
   $var wire 1 + clk $end
   $var wire 1 , rst_n $end
   $var wire 1 - w_ready $end
   $var wire 1 . w_valid $end
   $var wire 8 / w_data [7:0] $end
   $var wire 1 0 r_ready $end
   $var wire 1 1 r_valid $end
   $var wire 8 2 r_data [7:0] $end
   $var wire 8 3 R[0] [7:0] $end
   $var wire 8 4 R[1] [7:0] $end
   $var wire 8 5 R[2] [7:0] $end
   $var wire 8 6 R[3] [7:0] $end
   $var wire 8 7 R[4] [7:0] $end
   $var wire 8 8 R[5] [7:0] $end
   $var wire 8 9 R[6] [7:0] $end
   $var wire 8 : R[7] [7:0] $end
   $var wire 8 ; R_nxt[0] [7:0] $end
   $var wire 8 < R_nxt[1] [7:0] $end
   $var wire 8 = R_nxt[2] [7:0] $end
   $var wire 8 > R_nxt[3] [7:0] $end
   $var wire 8 ? R_nxt[4] [7:0] $end
   $var wire 8 @ R_nxt[5] [7:0] $end
   $var wire 8 A R_nxt[6] [7:0] $end
   $var wire 8 B R_nxt[7] [7:0] $end
   $var wire 8 C r_data_nxt [7:0] $end
   $var wire 4 D wp [3:0] $end
   $var wire 4 E wp_nxt [3:0] $end
   $var wire 4 F rp [3:0] $end
   $var wire 4 G rp_nxt [3:0] $end
   $var wire 1 H w_fire $end
   $var wire 1 I r_fire $end
   $var wire 32 J i [31:0] $end
  $upscope $end
  $var wire 1 # clk $end
  $var wire 1 $ rst_n $end
  $var wire 1 % w_ready $end
  $var wire 1 & w_valid $end
  $var wire 8 ' w_data [7:0] $end
  $var wire 1 ( r_ready $end
  $var wire 1 ) r_valid $end
  $var wire 8 * r_data [7:0] $end
 $upscope $end
$enddefinitions $end


#5
0#
0$
1%
0&
b00000000 '
0(
0)
b00000000 *
0+
0,
1-
0.
b00000000 /
00
01
b00000000 2
b00000000 3
b00000000 4
b00000000 5
b00000000 6
b00000000 7
b00000000 8
b00000000 9
b00000000 :
b00000000 ;
b00000000 <
b00000000 =
b00000000 >
b00000000 ?
b00000000 @
b00000000 A
b00000000 B
b00000000 C
b0000 D
b0000 E
b0000 F
b0000 G
0H
0I
b00000000000000000000000000001000 J
#10
1#
1+
#15
0#
1$
0+
1,
#20
1#
1+
#25
0#
1&
b00001010 '
0+
1.
b00001010 /
b00001010 ;
b0001 E
1H
#30
1#
1(
1+
10
b00001010 3
b00001010 <
b0001 D
b0010 E
#35
0#
0&
0+
0.
b00000000 <
b0001 E
0H
#40
1#
1+
#45
0#
0+
#50
1#
1+
#55
0#
1&
b00001011 '
0+
1.
b00001011 /
b00001011 <
b0010 E
1H
#60
1#
1+
b00001011 4
b00001011 =
b0010 D
b0011 E
#65
0#
0&
0+
0.
b00000000 =
b0010 E
0H
#70
1#
1+
#75
0#
0+
#80
1#
1+
#85
0#
1)
0+
11
b00001010 C
b0001 G
1I
#90
1#
b00001010 *
1+
b00001010 2
b00001011 C
b0001 F
b0010 G
#95
0#
0)
0+
01
b00000000 C
b0001 G
0I
#100
1#
b00000000 *
1+
b00000000 2
#105
0#
0+
#110
1#
1+
#115
0#
1)
0+
11
b00001011 C
b0010 G
1I
#120
1#
0(
b00001011 *
1+
00
b00001011 2
b00000000 C
b0010 F
0I
#125
0#
0+
#130
1#
b00000000 *
1+
b00000000 2
