labs_backup/backup_lab08/pr_sorter_id/design_src/sorter_id.v
module sorter_id (
    input  [3:0] v0, v1, v2, v3,
    output [3:0] o0, o1, o2, o3,
    output [1:0] o3_id
);
    wire [3:0] c0_min   , c0_max   , c1_min   , c1_max   , c2_min,
               c3_min   , c3_max   , c4_min   ;
    wire [3:0] c0_min_id, c0_max_id, c1_min_id, c1_max_id, c2_min_id,
               c3_min_id, c3_max_id, c4_min_id;

    cmp_id c0 (.a(    v0), .b(    v1), .a_id(     2'd0), .b_id(     2'd1), .min(c0_min), .max(c0_max), .min_id(c0_min_id), .max_id(c0_max_id));
    cmp_id c1 (.a(c0_max), .b(    v2), .a_id(c0_max_id), .b_id(     2'd2), .min(c1_min), .max(c1_max), .min_id(c1_min_id), .max_id(c1_max_id));
    cmp_id c2 (.a(c1_max), .b(    v3), .a_id(c1_max_id), .b_id(     2'd3), .min(c2_min), .max(    o3), .min_id(c2_min_id), .max_id(    o3_id));
    cmp_id c3 (.a(c0_min), .b(c1_min), .a_id(c0_min_id), .b_id(c1_min_id), .min(c3_min), .max(c3_max), .min_id(c3_min_id), .max_id(c3_max_id));
    cmp_id c4 (.a(c3_max), .b(c2_min), .a_id(c3_max_id), .b_id(c2_min_id), .min(c4_min), .max(    o2), .min_id(c4_min_id), .max_id(         ));
    cmp_id c5 (.a(c3_min), .b(c4_min), .a_id(c3_min_id), .b_id(c4_min_id), .min(    o0), .max(    o1), .min_id(         ), .max_id(         ));
endmodule


module cmp_id (
    input  unsigned [3:0] a,
    input  unsigned [3:0] b,
    input  unsigned [1:0] a_id,
    input  unsigned [1:0] b_id,
    output reg [3:0] min,
    output reg [3:0] max,
    output reg [1:0] min_id,
    output reg [1:0] max_id
);
    reg a_is_max;
    always @(*) begin
        a_is_max = {a, a_id} > {b, b_id};
        min    = a_is_max ? b : a;
        max    = a_is_max ? a : b;
        min_id = a_is_max ? b_id : a_id;
        max_id = a_is_max ? a_id : b_id;
    end
endmodule

labs_backup/backup_lab08/pr_sorter_id/sim_result/wave.vcd
$version Generated by VerilatedVcd $end
$timescale 1ps $end
 $scope module TOP $end
  $var wire 4 # v0 [3:0] $end
  $var wire 4 $ v1 [3:0] $end
  $var wire 4 % v2 [3:0] $end
  $var wire 4 & v3 [3:0] $end
  $var wire 4 ' o0 [3:0] $end
  $var wire 4 ( o1 [3:0] $end
  $var wire 4 ) o2 [3:0] $end
  $var wire 4 * o3 [3:0] $end
  $var wire 2 + o3_id [1:0] $end
  $scope module sorter_id $end
   $var wire 4 , v0 [3:0] $end
   $var wire 4 - v1 [3:0] $end
   $var wire 4 . v2 [3:0] $end
   $var wire 4 / v3 [3:0] $end
   $var wire 4 0 o0 [3:0] $end
   $var wire 4 1 o1 [3:0] $end
   $var wire 4 2 o2 [3:0] $end
   $var wire 4 3 o3 [3:0] $end
   $var wire 2 4 o3_id [1:0] $end
   $var wire 4 5 c0_min [3:0] $end
   $var wire 4 6 c0_max [3:0] $end
   $var wire 4 7 c1_min [3:0] $end
   $var wire 4 8 c1_max [3:0] $end
   $var wire 4 9 c2_min [3:0] $end
   $var wire 4 : c3_min [3:0] $end
   $var wire 4 ; c3_max [3:0] $end
   $var wire 4 < c4_min [3:0] $end
   $var wire 4 = c0_min_id [3:0] $end
   $var wire 4 > c0_max_id [3:0] $end
   $var wire 4 ? c1_min_id [3:0] $end
   $var wire 4 @ c1_max_id [3:0] $end
   $var wire 4 A c2_min_id [3:0] $end
   $var wire 4 B c3_min_id [3:0] $end
   $var wire 4 C c3_max_id [3:0] $end
   $var wire 4 D c4_min_id [3:0] $end
   $scope module c0 $end
    $var wire 4 E a [3:0] $end
    $var wire 4 F b [3:0] $end
    $var wire 2 G a_id [1:0] $end
    $var wire 2 H b_id [1:0] $end
    $var wire 4 I min [3:0] $end
    $var wire 4 J max [3:0] $end
    $var wire 2 K min_id [1:0] $end
    $var wire 2 L max_id [1:0] $end
    $var wire 1 M a_is_max $end
   $upscope $end
   $scope module c1 $end
    $var wire 4 N a [3:0] $end
    $var wire 4 O b [3:0] $end
    $var wire 2 P a_id [1:0] $end
    $var wire 2 Q b_id [1:0] $end
    $var wire 4 R min [3:0] $end
    $var wire 4 S max [3:0] $end
    $var wire 2 T min_id [1:0] $end
    $var wire 2 U max_id [1:0] $end
    $var wire 1 V a_is_max $end
   $upscope $end
   $scope module c2 $end
    $var wire 4 W a [3:0] $end
    $var wire 4 X b [3:0] $end
    $var wire 2 Y a_id [1:0] $end
    $var wire 2 Z b_id [1:0] $end
    $var wire 4 [ min [3:0] $end
    $var wire 4 \ max [3:0] $end
    $var wire 2 ] min_id [1:0] $end
    $var wire 2 ^ max_id [1:0] $end
    $var wire 1 _ a_is_max $end
   $upscope $end
   $scope module c3 $end
    $var wire 4 ` a [3:0] $end
    $var wire 4 a b [3:0] $end
    $var wire 2 b a_id [1:0] $end
    $var wire 2 c b_id [1:0] $end
    $var wire 4 d min [3:0] $end
    $var wire 4 e max [3:0] $end
    $var wire 2 f min_id [1:0] $end
    $var wire 2 g max_id [1:0] $end
    $var wire 1 h a_is_max $end
   $upscope $end
   $scope module c4 $end
    $var wire 4 i a [3:0] $end
    $var wire 4 j b [3:0] $end
    $var wire 2 k a_id [1:0] $end
    $var wire 2 l b_id [1:0] $end
    $var wire 4 m min [3:0] $end
    $var wire 4 n max [3:0] $end
    $var wire 2 o min_id [1:0] $end
    $var wire 2 p max_id [1:0] $end
    $var wire 1 q a_is_max $end
   $upscope $end
   $scope module c5 $end
    $var wire 4 r a [3:0] $end
    $var wire 4 s b [3:0] $end
    $var wire 2 t a_id [1:0] $end
    $var wire 2 u b_id [1:0] $end
    $var wire 4 v min [3:0] $end
    $var wire 4 w max [3:0] $end
    $var wire 2 x min_id [1:0] $end
    $var wire 2 y max_id [1:0] $end
    $var wire 1 z a_is_max $end
   $upscope $end
  $upscope $end
 $upscope $end
$enddefinitions $end


#0
b1100 #
b1111 $
b1001 %
b0000 &
b0000 '
b1001 (
b1100 )
b1111 *
b01 +
b1100 ,
b1111 -
b1001 .
b0000 /
b0000 0
b1001 1
b1100 2
b1111 3
b01 4
b1100 5
b1111 6
b1001 7
b1111 8
b0000 9
b1001 :
b1100 ;
b0000 <
b0000 =
b0001 >
b0010 ?
b0001 @
b0011 A
b0010 B
b0000 C
b0011 D
b1100 E
b1111 F
b00 G
b01 H
b1100 I
b1111 J
b00 K
b01 L
0M
b1111 N
b1001 O
b01 P
b10 Q
b1001 R
b1111 S
b10 T
b01 U
1V
b1111 W
b0000 X
b01 Y
b11 Z
b0000 [
b1111 \
b11 ]
b01 ^
1_
b1100 `
b1001 a
b00 b
b10 c
b1001 d
b1100 e
b10 f
b00 g
1h
b1100 i
b0000 j
b00 k
b11 l
b0000 m
b1100 n
b11 o
b00 p
1q
b1001 r
b0000 s
b10 t
b11 u
b0000 v
b1001 w
b11 x
b10 y
1z
#10
b0110 $
b0010 %
b1000 &
b0010 '
b0110 (
b1000 )
b1100 *
b00 +
b0110 -
b0010 .
b1000 /
b0010 0
b0110 1
b1000 2
b1100 3
b00 4
b0110 5
b1100 6
b0010 7
b1100 8
b1000 9
b0010 :
b0110 ;
b0110 <
b0001 =
b0000 >
b0000 @
b0001 C
b0001 D
b0110 F
b0110 I
b1100 J
b01 K
b00 L
1M
b1100 N
b0010 O
b00 P
b0010 R
b1100 S
b00 U
b1100 W
b1000 X
b00 Y
b1000 [
b1100 \
b00 ^
b0110 `
b0010 a
b01 b
b0010 d
b0110 e
b01 g
b0110 i
b1000 j
b01 k
b0110 m
b1000 n
b01 o
b11 p
0q
b0010 r
b0110 s
b01 u
b0010 v
b0110 w
b10 x
b01 y
0z
#20
b0100 #
b1010 $
b0101 %
b1010 &
b0100 '
b0101 (
b1010 )
b1010 *
b11 +
b0100 ,
b1010 -
b0101 .
b1010 /
b0100 0
b0101 1
b1010 2
b1010 3
b11 4
b0100 5
b1010 6
b0101 7
b1010 8
b1010 9
b0100 :
b0101 ;
b0101 <
b0000 =
b0001 >
b0001 @
b0001 A
b0000 B
b0010 C
b0010 D
b0100 E
b1010 F
b0100 I
b1010 J
b00 K
b01 L
0M
b1010 N
b0101 O
b01 P
b0101 R
b1010 S
b01 U
b1010 W
b1010 X
b01 Y
b1010 [
b1010 \
b01 ]
b11 ^
0_
b0100 `
b0101 a
b00 b
b0100 d
b0101 e
b00 f
b10 g
0h
b0101 i
b1010 j
b10 k
b01 l
b0101 m
b1010 n
b10 o
b01 p
b0100 r
b0101 s
b00 t
b10 u
b0100 v
b0101 w
b00 x
b10 y
#30
b1000 $
b0110 %
b0000 &
b0000 '
b0100 (
b0110 )
b1000 *
b01 +
b1000 -
b0110 .
b0000 /
b0000 0
b0100 1
b0110 2
b1000 3
b01 4
b1000 6
b0110 7
b1000 8
b0000 9
b0110 ;
b0000 <
b0011 A
b0011 D
b1000 F
b1000 J
b1000 N
b0110 O
b0110 R
b1000 S
b1000 W
b0000 X
b0000 [
b1000 \
b11 ]
b01 ^
1_
b0110 a
b0110 e
b0110 i
b0000 j
b11 l
b0000 m
b0110 n
b11 o
b10 p
1q
b0000 s
b11 u
b0000 v
b0100 w
b11 x
b00 y
1z
#40
b1110 #
b0111 $
b0100 %
b1000 &
b0100 '
b0111 (
b1000 )
b1110 *
b00 +
b1110 ,
b0111 -
b0100 .
b1000 /
b0100 0
b0111 1
b1000 2
b1110 3
b00 4
b0111 5
b1110 6
b0100 7
b1110 8
b1000 9
b0111 ;
b0111 <
b0001 =
b0000 >
b0000 @
b0010 B
b0001 C
b0001 D
b1110 E
b0111 F
b0111 I
b1110 J
b01 K
b00 L
1M
b1110 N
b0100 O
b00 P
b0100 R
b1110 S
b00 U
b1110 W
b1000 X
b00 Y
b1000 [
b1110 \
b00 ^
b0111 `
b0100 a
b01 b
b0111 e
b10 f
b01 g
1h
b0111 i
b1000 j
b01 k
b0111 m
b1000 n
b01 o
b11 p
0q
b0111 s
b10 t
b01 u
b0100 v
b0111 w
b10 x
b01 y
0z
#50
b0101 #
b1101 $
b0111 %
b1100 &
b0101 '
b1100 )
b1101 *
b01 +
b0101 ,
b1101 -
b0111 .
b1100 /
b0101 0
b1100 2
b1101 3
b01 4
b0101 5
b1101 6
b0111 7
b1101 8
b1100 9
b0101 :
b0000 =
b0001 >
b0001 @
b0000 B
b0010 C
b0010 D
b0101 E
b1101 F
b0101 I
b1101 J
b00 K
b01 L
0M
b1101 N
b0111 O
b01 P
b0111 R
b1101 S
b01 U
b1101 W
b1100 X
b01 Y
b1100 [
b1101 \
b01 ^
b0101 `
b0111 a
b00 b
b0101 d
b00 f
b10 g
0h
b1100 j
b10 k
b1100 n
b10 o
b0101 r
b00 t
b10 u
b0101 v
b00 x
b10 y
#60
b1001 #
b0010 %
b0100 &
b0010 '
b0100 (
b1001 )
b1001 ,
b0010 .
b0100 /
b0010 0
b0100 1
b1001 2
b1001 5
b0010 7
b0100 9
b0010 :
b1001 ;
b0100 <
b0010 B
b0000 C
b0011 D
b1001 E
b1001 I
b0010 O
b0010 R
b0100 X
b0100 [
b1001 `
b0010 a
b0010 d
b1001 e
b10 f
b00 g
1h
b1001 i
b0100 j
b00 k
b0100 m
b1001 n
b11 o
b00 p
1q
b0010 r
b0100 s
b10 t
b11 u
b0010 v
b0100 w
b10 x
b11 y
#70
b0010 #
b0001 $
b1111 %
b0001 &
b0001 '
b0001 (
b0010 )
b1111 *
b10 +
b0010 ,
b0001 -
b1111 .
b0001 /
b0001 0
b0001 1
b0010 2
b1111 3
b10 4
b0001 5
b0010 6
b1111 8
b0001 9
b0001 :
b0010 ;
b0001 <
b0001 =
b0000 >
b0000 ?
b0010 @
b0001 B
b0010 E
b0001 F
b0001 I
b0010 J
b01 K
b00 L
1M
b0010 N
b1111 O
b00 P
b1111 S
b00 T
b10 U
0V
b1111 W
b0001 X
b10 Y
b0001 [
b1111 \
b10 ^
b0001 `
b01 b
b00 c
b0001 d
b0010 e
b01 f
0h
b0010 i
b0001 j
b0001 m
b0010 n
b0001 r
b0001 s
b01 t
b0001 v
b0001 w
b01 x
#80
b1010 #
b0101 $
b0111 %
b0101 (
b0111 )
b1010 *
b00 +
b1010 ,
b0101 -
b0111 .
b0101 1
b0111 2
b1010 3
b00 4
b0101 5
b1010 6
b0111 7
b1010 8
b0101 :
b0111 ;
b0010 ?
b0000 @
b0010 C
b1010 E
b0101 F
b0101 I
b1010 J
b1010 N
b0111 O
b0111 R
b1010 S
b10 T
b00 U
1V
b1010 W
b00 Y
b1010 \
b00 ^
b0101 `
b0111 a
b10 c
b0101 d
b0111 e
b10 g
b0111 i
b10 k
b0111 n
b10 p
b0101 r
b0101 w
b11 x
b01 y
1z
#90
b1111 #
b1011 $
b0100 %
b1001 &
b0100 '
b1001 (
b1011 )
b1111 *
b1111 ,
b1011 -
b0100 .
b1001 /
b0100 0
b1001 1
b1011 2
b1111 3
b1011 5
b1111 6
b0100 7
b1111 8
b1001 9
b0100 :
b1011 ;
b1001 <
b0010 B
b0001 C
b1111 E
b1011 F
b1011 I
b1111 J
b1111 N
b0100 O
b0100 R
b1111 S
b1111 W
b1001 X
b1001 [
b1111 \
b1011 `
b0100 a
b0100 d
b1011 e
b10 f
b01 g
1h
b1011 i
b1001 j
b01 k
b1001 m
b1011 n
b01 p
b0100 r
b1001 s
b10 t
b0100 v
b1001 w
b10 x
b11 y
0z
#100
b0000 #
b0000 $
b0000 %
b0000 &
b0000 '
b0000 (
b0000 )
b0000 *
b11 +
b0000 ,
b0000 -
b0000 .
b0000 /
b0000 0
b0000 1
b0000 2
b0000 3
b11 4
b0000 5
b0000 6
b0000 7
b0000 8
b0000 9
b0000 :
b0000 ;
b0000 <
b0000 =
b0001 >
b0001 ?
b0010 @
b0010 A
b0000 B
b0001 D
b0000 E
b0000 F
b0000 I
b0000 J
b00 K
b01 L
0M
b0000 N
b0000 O
b01 P
b0000 R
b0000 S
b01 T
b10 U
0V
b0000 W
b0000 X
b10 Y
b0000 [
b0000 \
b10 ]
b11 ^
0_
b0000 `
b0000 a
b00 b
b01 c
b0000 d
b0000 e
b00 f
0h
b0000 i
b0000 j
b10 l
b0000 m
b0000 n
b01 o
b10 p
0q
b0000 r
b0000 s
b00 t
b01 u
b0000 v
b0000 w
b00 x
b01 y
#110
b1111 #
b1111 $
b1111 %
b1111 &
b1111 '
b1111 (
b1111 )
b1111 *
b1111 ,
b1111 -
b1111 .
b1111 /
b1111 0
b1111 1
b1111 2
b1111 3
b1111 5
b1111 6
b1111 7
b1111 8
b1111 9
b1111 :
b1111 ;
b1111 <
b1111 E
b1111 F
b1111 I
b1111 J
b1111 N
b1111 O
b1111 R
b1111 S
b1111 W
b1111 X
b1111 [
b1111 \
b1111 `
b1111 a
b1111 d
b1111 e
b1111 i
b1111 j
b1111 m
b1111 n
b1111 r
b1111 s
b1111 v
b1111 w
#120
b0101 #
b0101 $
b0101 %
b0100 &
b0100 '
b0101 (
b0101 )
b0101 *
b10 +
b0101 ,
b0101 -
b0101 .
b0100 /
b0100 0
b0101 1
b0101 2
b0101 3
b10 4
b0101 5
b0101 6
b0101 7
b0101 8
b0100 9
b0101 :
b0101 ;
b0100 <
b0011 A
b0011 D
b0101 E
b0101 F
b0101 I
b0101 J
b0101 N
b0101 O
b0101 R
b0101 S
b0101 W
b0100 X
b0100 [
b0101 \
b11 ]
b10 ^
1_
b0101 `
b0101 a
b0101 d
b0101 e
b0101 i
b0100 j
b11 l
b0100 m
b0101 n
b11 o
b01 p
1q
b0101 r
b0100 s
b11 u
b0100 v
b0101 w
b11 x
b00 y
1z
#130
b0001 #
b0010 $
b0010 %
b0010 &
b0001 '
b0010 (
b0010 )
b0010 *
b11 +
b0001 ,
b0010 -
b0010 .
b0010 /
b0001 0
b0010 1
b0010 2
b0010 3
b11 4
b0001 5
b0010 6
b0010 7
b0010 8
b0010 9
b0001 :
b0010 ;
b0010 <
b0010 A
b0001 D
b0001 E
b0010 F
b0001 I
b0010 J
b0010 N
b0010 O
b0010 R
b0010 S
b0010 W
b0010 X
b0010 [
b0010 \
b10 ]
b11 ^
0_
b0001 `
b0010 a
b0001 d
b0010 e
b0010 i
b0010 j
b10 l
b0010 m
b0010 n
b01 o
b10 p
0q
b0001 r
b0010 s
b01 u
b0001 v
b0010 w
b00 x
b01 y
0z
#140
b0011 #
b0001 %
b0011 &
b0011 )
b0011 *
b0011 ,
b0001 .
b0011 /
b0011 2
b0011 3
b0010 5
b0011 6
b0001 7
b0011 8
b0011 9
b0001 =
b0000 >
b0010 ?
b0000 @
b0000 A
b0010 B
b0011 E
b0010 I
b0011 J
b01 K
b00 L
1M
b0011 N
b0001 O
b00 P
b0001 R
b0011 S
b10 T
b00 U
1V
b0011 W
b0011 X
b00 Y
b0011 [
b0011 \
b00 ]
b0010 `
b0001 a
b01 b
b10 c
b10 f
1h
b0011 j
b00 l
b0011 n
b00 p
b10 t
b10 x
#150
b0111 #
b0111 $
b0101 %
b0111 &
b0101 '
b0111 (
b0111 )
b0111 *
b0111 ,
b0111 -
b0101 .
b0111 /
b0101 0
b0111 1
b0111 2
b0111 3
b0111 5
b0111 6
b0101 7
b0111 8
b0111 9
b0101 :
b0111 ;
b0111 <
b0000 =
b0001 >
b0001 @
b0001 A
b0000 C
b0000 D
b0111 E
b0111 F
b0111 I
b0111 J
b00 K
b01 L
0M
b0111 N
b0101 O
b01 P
b0101 R
b0111 S
b01 U
b0111 W
b0111 X
b01 Y
b0111 [
b0111 \
b01 ]
b0111 `
b0101 a
b00 b
b0101 d
b0111 e
b00 g
b0111 i
b0111 j
b00 k
b01 l
b0111 m
b0111 n
b00 o
b01 p
b0101 r
b0111 s
b00 u
b0101 v
b0111 w
b00 y
#160
b0000 #
b1111 $
b0000 %
b1111 &
b0000 '
b0000 (
b1111 )
b1111 *
b0000 ,
b1111 -
b0000 .
b1111 /
b0000 0
b0000 1
b1111 2
b1111 3
b0000 5
b1111 6
b0000 7
b1111 8
b1111 9
b0000 :
b0000 ;
b0000 <
b0000 B
b0010 C
b0010 D
b0000 E
b1111 F
b0000 I
b1111 J
b1111 N
b0000 O
b0000 R
b1111 S
b1111 W
b1111 X
b1111 [
b1111 \
b0000 `
b0000 a
b0000 d
b0000 e
b00 f
b10 g
0h
b0000 i
b1111 j
b10 k
b0000 m
b1111 n
b10 o
b0000 r
b0000 s
b00 t
b10 u
b0000 v
b0000 w
b00 x
b10 y
#170
b1001 #
b1000 $
b1001 %
b0111 &
b0111 '
b1000 (
b1001 )
b1001 *
b10 +
b1001 ,
b1000 -
b1001 .
b0111 /
b0111 0
b1000 1
b1001 2
b1001 3
b10 4
b1000 5
b1001 6
b1001 7
b1001 8
b0111 9
b1000 :
b1001 ;
b0111 <
b0001 =
b0000 >
b0000 ?
b0010 @
b0011 A
b0001 B
b0000 C
b0011 D
b1001 E
b1000 F
b1000 I
b1001 J
b01 K
b00 L
1M
b1001 N
b1001 O
b00 P
b1001 R
b1001 S
b00 T
b10 U
0V
b1001 W
b0111 X
b10 Y
b0111 [
b1001 \
b11 ]
b10 ^
1_
b1000 `
b1001 a
b01 b
b00 c
b1000 d
b1001 e
b01 f
b00 g
b1001 i
b0111 j
b00 k
b11 l
b0111 m
b1001 n
b11 o
b00 p
1q
b1000 r
b0111 s
b01 t
b11 u
b0111 v
b1000 w
b11 x
b01 y
1z
#180
b0110 #
b1110 $
b1110 %
b1101 &
b0110 '
b1101 (
b1110 )
b1110 *
b0110 ,
b1110 -
b1110 .
b1101 /
b0110 0
b1101 1
b1110 2
b1110 3
b0110 5
b1110 6
b1110 7
b1110 8
b1101 9
b0110 :
b1110 ;
b1101 <
b0000 =
b0001 >
b0001 ?
b0000 B
b0001 C
b0110 E
b1110 F
b0110 I
b1110 J
b00 K
b01 L
0M
b1110 N
b1110 O
b01 P
b1110 R
b1110 S
b01 T
b1110 W
b1101 X
b1101 [
b1110 \
b0110 `
b1110 a
b00 b
b01 c
b0110 d
b1110 e
b00 f
b01 g
b1110 i
b1101 j
b01 k
b1101 m
b1110 n
b01 p
b0110 r
b1101 s
b00 t
b0110 v
b1101 w
b00 x
b11 y
0z
#190
b1010 #
b1010 $
b1010 %
b1011 &
b1010 '
b1010 (
b1010 )
b1011 *
b11 +
b1010 ,
b1010 -
b1010 .
b1011 /
b1010 0
b1010 1
b1010 2
b1011 3
b11 4
b1010 5
b1010 6
b1010 7
b1010 8
b1010 9
b1010 :
b1010 ;
b1010 <
b0010 A
b0001 D
b1010 E
b1010 F
b1010 I
b1010 J
b1010 N
b1010 O
b1010 R
b1010 S
b1010 W
b1011 X
b1010 [
b1011 \
b10 ]
b11 ^
0_
b1010 `
b1010 a
b1010 d
b1010 e
b1010 i
b1010 j
b10 l
b1010 m
b1010 n
b01 o
b10 p
0q
b1010 r
b1010 s
b01 u
b1010 v
b1010 w
b01 y
